<?xml version='1.0' encoding='utf-8'?>
<TextureAtlas imagePath="NOTE_splashes_ORANGE-pixel.png">
<SubTexture name="note splash blue 10000" x="0" y="1015" width="308" height="301" frameX="-105" frameY="-133" frameWidth="518" frameHeight="546" />
<SubTexture name="note splash blue 10001" x="1022" y="0" width="301" height="378" frameX="-105" frameY="-91" frameWidth="518" frameHeight="546" />
<SubTexture name="note splash blue 10002" x="490" y="546" width="434" height="420" frameX="-42" frameY="-28" frameWidth="518" frameHeight="546" />
<SubTexture name="note splash blue 10003" x="518" y="0" width="504" height="497" frameX="-7" frameY="-35" frameWidth="518" frameHeight="546" />
<SubTexture name="note splash blue 10004" x="0" y="546" width="490" height="469" frameX="-14" frameY="-49" frameWidth="518" frameHeight="546" />
<SubTexture name="note splash blue 10005" x="0" y="0" width="518" height="546" frameX="0" frameY="0" frameWidth="518" frameHeight="546" />
<SubTexture name="note splash green 10000" x="0" y="1015" width="308" height="301" frameX="-105" frameY="-133" frameWidth="518" frameHeight="546" />
<SubTexture name="note splash green 10001" x="1022" y="0" width="301" height="378" frameX="-105" frameY="-91" frameWidth="518" frameHeight="546" />
<SubTexture name="note splash green 10002" x="490" y="546" width="434" height="420" frameX="-42" frameY="-28" frameWidth="518" frameHeight="546" />
<SubTexture name="note splash green 10003" x="518" y="0" width="504" height="497" frameX="-7" frameY="-35" frameWidth="518" frameHeight="546" />
<SubTexture name="note splash green 10004" x="0" y="546" width="490" height="469" frameX="-14" frameY="-49" frameWidth="518" frameHeight="546" />
<SubTexture name="note splash green 10005" x="0" y="0" width="518" height="546" frameX="0" frameY="0" frameWidth="518" frameHeight="546" />
<SubTexture name="note splash purple 10000" x="0" y="1015" width="308" height="301" frameX="-105" frameY="-133" frameWidth="518" frameHeight="546" />
<SubTexture name="note splash purple 10001" x="1022" y="0" width="301" height="378" frameX="-105" frameY="-91" frameWidth="518" frameHeight="546" />
<SubTexture name="note splash purple 10002" x="490" y="546" width="434" height="420" frameX="-42" frameY="-28" frameWidth="518" frameHeight="546" />
<SubTexture name="note splash purple 10003" x="518" y="0" width="504" height="497" frameX="-7" frameY="-35" frameWidth="518" frameHeight="546" />
<SubTexture name="note splash purple 10004" x="0" y="546" width="490" height="469" frameX="-14" frameY="-49" frameWidth="518" frameHeight="546" />
<SubTexture name="note splash purple 10005" x="0" y="0" width="518" height="546" frameX="0" frameY="0" frameWidth="518" frameHeight="546" />
<SubTexture name="note splash red 10000" x="0" y="1015" width="308" height="301" frameX="-105" frameY="-133" frameWidth="518" frameHeight="546" />
<SubTexture name="note splash red 10001" x="1022" y="0" width="301" height="378" frameX="-105" frameY="-91" frameWidth="518" frameHeight="546" />
<SubTexture name="note splash red 10002" x="490" y="546" width="434" height="420" frameX="-42" frameY="-28" frameWidth="518" frameHeight="546" />
<SubTexture name="note splash red 10003" x="518" y="0" width="504" height="497" frameX="-7" frameY="-35" frameWidth="518" frameHeight="546" />
<SubTexture name="note splash red 10004" x="0" y="546" width="490" height="469" frameX="-14" frameY="-49" frameWidth="518" frameHeight="546" />
<SubTexture name="note splash red 10005" x="0" y="0" width="518" height="546" frameX="0" frameY="0" frameWidth="518" frameHeight="546" />
</TextureAtlas>
