{"events":[{"params":[1],"name":"Camera Movement","time":0},{"params":[0],"time":0,"name":"stage swap"},{"params":[false,0],"time":61111.1111111111,"name":"character swap"},{"params":["revealDad",""],"time":61666.6666666667,"name":"HScript Call"},{"params":[0],"name":"Camera Movement","time":61666.6666666667},{"params":[],"name":"trippy","time":63333.3333333333},{"params":[],"time":66111.1111111111,"name":"trippy"},{"params":[],"name":"trippy","time":67222.2222222222},{"params":["notePlace","1"],"time":75555.5555555555,"name":"HScript Call"},{"params":[1],"name":"Camera Movement","time":76666.6666666667},{"params":[false,-16777216,8,"camGame"],"time":76666.6666666667,"name":"Camera Flash"},{"params":[true,2,1],"time":88333.3333333333,"name":"setCharZoom"},{"params":[0],"name":"Camera Movement","time":90000},{"params":[true,0.4,20],"time":90000,"name":"setCharZoom"},{"params":[1],"name":"Camera Movement","time":103333.333333333},{"params":["notePlace","0"],"name":"HScript Call","time":117777.777777778},{"params":["heGoes",""],"time":118888.888888889,"name":"HScript Call"},{"params":[true,-16777216,8,"camHUD"],"time":118888.888888889,"name":"Camera Flash"},{"params":[0],"name":"Camera Movement","time":120000},{"params":["baseDrop",""],"time":120000,"name":"HScript Call"},{"params":[false,1],"name":"character swap","time":120000},{"params":[1],"time":120000,"name":"stage swap"},{"params":[true,true,1],"name":"Alt Animation Toggle","time":120000},{"params":["1,0.44,0.05",true],"name":"FD flicker","time":120000},{"params":["showMoreHud",""],"name":"HScript Call","time":120000},{"params":[true,3.1,8,"expo","InOut"],"name":"Scroll Speed Change","time":120000},{"params":["trails","true"],"name":"HScript Call","time":120000},{"params":[1],"time":121111.111111111,"name":"Camera Movement"},{"params":[0],"name":"Camera Movement","time":122222.222222222},{"params":[1],"name":"Camera Movement","time":123333.333333333},{"params":[0],"time":124444.444444444,"name":"Camera Movement"},{"params":[1],"name":"Camera Movement","time":125555.555555556},{"params":[0],"name":"Camera Movement","time":126666.666666667},{"params":[1],"name":"Camera Movement","time":128888.888888889},{"params":["1,0.44,0.05",true],"name":"FD flicker","time":128888.888888889},{"params":[0],"name":"Camera Movement","time":130000},{"params":[1],"time":131111.111111111,"name":"Camera Movement"},{"params":[0],"name":"Camera Movement","time":132222.222222222},{"params":[1],"name":"Camera Movement","time":133333.333333333},{"params":["notePlace","0"],"time":133333.333333333,"name":"HScript Call"},{"params":[0],"name":"Camera Movement","time":134444.444444444},{"params":[1],"time":135555.555555556,"name":"Camera Movement"},{"params":[0],"name":"Camera Movement","time":137777.777777778},{"params":["setGlitchAmt","1.6,0.00001,2"],"name":"HScript Call","time":137777.777777778},{"params":["bBox",""],"name":"HScript Call","time":137777.777777778},{"params":[true],"name":"Inverted","time":137777.777777778},{"params":["setGlitchAmt","1,0.9,2"],"time":138888.888888889,"name":"HScript Call"},{"params":["setGlitchAmt","0.5,0.9,2"],"name":"HScript Call","time":139444.444444444},{"params":["setGlitchAmt","0.05,0.9,2"],"name":"HScript Call","time":140000},{"params":["bBox",""],"name":"HScript Call","time":140000},{"params":[1],"name":"Camera Movement","time":142222.222222222},{"params":[false,2],"name":"character swap","time":142222.222222222},{"params":[0,"change",true],"name":"Play Animation","time":142222.222222222},{"params":["bBox",""],"name":"HScript Call","time":142222.222222222},{"params":[0],"name":"Camera Movement","time":144444.444444444},{"params":["bBox",""],"name":"HScript Call","time":144444.444444444},{"params":[false,0.7,21],"name":"setCharZoom","time":146111.111111111},{"params":[false,3],"name":"character swap","time":146666.666666667},{"params":[2],"name":"stage swap","time":146666.666666667},{"params":["hideHud","true"],"name":"HScript Call","time":146666.666666667},{"params":["setGlitchAmt","0.2,0.001,2"],"name":"HScript Call","time":146666.666666667},{"params":["bBox","end"],"name":"HScript Call","time":146666.666666667},{"params":["swapTrails","dad"],"name":"HScript Call","time":146666.666666667},{"params":["img6",""],"name":"HScript Call","time":146666.666666667},{"params":[true],"name":"Inverted","time":155277.777777778},{"params":["hideHud","false,3"],"name":"HScript Call","time":155555.555555556},{"params":["setGlitchAmt","0.02,0.0,2"],"name":"HScript Call","time":155555.555555556},{"params":[false,0.8,19],"name":"setCharZoom","time":155555.555555556},{"params":["img3",""],"name":"HScript Call","time":155555.555555556},{"params":[false,0.9,19],"name":"setCharZoom","time":157777.777777778},{"params":[false,1,19],"time":160000,"name":"setCharZoom"},{"params":["notePlace","2"],"name":"HScript Call","time":161944.444444444},{"params":[false,1.1,2],"name":"setCharZoom","time":162222.222222222},{"params":["zoomPart",""],"name":"HScript Call","time":163055.555555556},{"params":["hideStage","2"],"time":163333.333333333,"name":"HScript Call"},{"params":[false,20,29],"time":163333.333333333,"name":"setCharZoom"},{"params":[1],"name":"Camera Movement","time":164444.444444444},{"params":[false,-1,4,"camGame"],"time":164444.444444444,"name":"Camera Flash"},{"params":[false,0.57,40],"time":164444.444444444,"name":"setCharZoom"},{"params":["setBack",""],"name":"HScript Call","time":164444.444444444},{"params":["setGlitchAmt","0.01,0.0,2"],"name":"HScript Call","time":164444.444444444},{"params":["hideStage","1"],"name":"HScript Call","time":164444.444444444},{"params":[2],"time":164583.333333333,"name":"stage swap"},{"params":[0],"time":173611.111111111,"name":"Camera Movement"},{"params":["notePlace","0"],"time":176666.666666667,"name":"HScript Call"},{"params":[false,-1,14,"camGame"],"name":"Camera Flash","time":182222.222222222},{"params":[1],"time":182500,"name":"Camera Movement"},{"params":[0],"name":"Camera Movement","time":191111.111111111},{"params":["notePlace","3"],"time":191111.111111111,"name":"HScript Call"},{"params":[1],"time":195555.555555556,"name":"Camera Movement"},{"params":[true,0.35,9],"name":"setCharZoom","time":199444.444444444},{"params":[6],"name":"stage swap","time":200000},{"params":["setGlitchAmt","0.02,0.15"],"name":"HScript Call","time":200000},{"params":[true],"name":"Inverted","time":200000},{"params":[true,0.4,9],"name":"setCharZoom","time":200000},{"params":[0],"name":"Camera Movement","time":203611.111111111},{"params":[1],"time":204444.444444444,"name":"Camera Movement"},{"params":[0],"name":"Camera Movement","time":207777.777777778},{"params":[1],"name":"Camera Movement","time":215555.555555555},{"params":["setGlitchAmt","8,1.0,2"],"name":"HScript Call","time":217777.777777778},{"params":["blackOut","1"],"name":"HScript Call","time":218333.333333333},{"params":["setGlitchAmt","0.3,0.0,2"],"time":221111.111111111,"name":"HScript Call"},{"params":["notePlace","1"],"time":221388.888888889,"name":"HScript Call"},{"params":[7],"name":"stage swap","time":222222.222222222},{"params":["blackOut","0"],"name":"HScript Call","time":222222.222222222},{"params":["setGlitchAmt","0.01,0.2,2"],"name":"HScript Call","time":222222.222222222},{"params":["setGlitchAmt","0.25,0.0,2"],"name":"HScript Call","time":222500},{"params":["setGlitchAmt","0.15,0.0,2"],"time":223055.555555556,"name":"HScript Call"},{"params":["setGlitchAmt","0.05,0.0,2"],"name":"HScript Call","time":223611.111111111},{"params":[0],"name":"Camera Movement","time":231111.111111111},{"params":[1],"name":"Camera Movement","time":237777.777777777},{"params":["img1",""],"name":"HScript Call","time":239444.444444444},{"params":[5],"time":240000,"name":"stage swap"},{"params":[0],"time":240000,"name":"Camera Movement"},{"params":["swapTrails","bf"],"name":"HScript Call","time":240000},{"params":[1],"time":244444.444444444,"name":"Camera Movement"},{"params":[0],"name":"Camera Movement","time":248888.888888889},{"params":[1],"time":253333.333333333,"name":"Camera Movement"},{"params":[0],"time":257777.777777778,"name":"Camera Movement"},{"params":["img2",""],"time":257777.777777778,"name":"HScript Call"},{"params":["img3",""],"time":260000,"name":"HScript Call"},{"params":[1],"name":"Camera Movement","time":262222.222222222},{"params":["img4",""],"time":264444.444444444,"name":"HScript Call"},{"params":[0],"time":266666.666666667,"name":"Camera Movement"},{"params":["img5",""],"time":266666.666666667,"name":"HScript Call"},{"params":[1],"name":"Camera Movement","time":267777.777777778},{"params":[0],"name":"Camera Movement","time":268888.888888889},{"params":["img6",""],"time":268888.888888889,"name":"HScript Call"},{"params":[1],"time":269861.111111111,"name":"Camera Movement"},{"params":[0],"name":"Camera Movement","time":272083.333333333},{"params":["img4",""],"time":272222.222222222,"name":"HScript Call"},{"params":[1],"name":"Camera Movement","time":273333.333333333},{"params":["img4",""],"time":274027.777777778,"name":"HScript Call"},{"params":["img5",""],"name":"HScript Call","time":274166.666666667},{"params":["img6",""],"time":274305.555555556,"name":"HScript Call"},{"params":[0],"time":275555.555555556,"name":"Camera Movement"},{"params":[5],"time":275555.555555556,"name":"stage swap"},{"params":["img22",""],"time":275555.555555556,"name":"HScript Call"},{"params":["endVid",""],"time":275555.555555556,"name":"HScript Call"},{"params":[1],"name":"Camera Movement","time":277777.777777778},{"params":[0],"name":"Camera Movement","time":280000},{"params":[1],"name":"Camera Movement","time":282222.222222222},{"params":["img4",""],"time":284444.444444444,"name":"HScript Call"},{"params":["img5",""],"time":286666.666666667,"name":"HScript Call"},{"params":[1],"time":288888.888888889,"name":"Camera Movement"},{"params":["scream","0"],"name":"HScript Call","time":291111.111111111},{"params":["scream","1"],"time":292222.222222222,"name":"HScript Call"},{"params":[true,-1,4,"camGame"],"name":"Camera Flash","time":292777.777777778},{"params":[1],"name":"Camera Movement","time":293333.333333333},{"params":["img3",""],"name":"HScript Call","time":293333.333333333},{"params":[0],"name":"Camera Movement","time":295555.555555556},{"params":[1],"name":"Camera Movement","time":300000},{"params":[0],"name":"Camera Movement","time":308888.888888889},{"params":["setGlitchAmt","1.0,0,2"],"name":"HScript Call","time":309444.444444444},{"params":["setGlitchAmt","2.0,0,2"],"time":310000,"name":"HScript Call"},{"params":["gazerCamG",""],"time":310000,"name":"HScript Call"},{"params":[0.05,"camGame"],"name":"Add Camera Zoom","time":310000},{"params":["img6",""],"name":"HScript Call","time":310000},{"params":[0.05,"camGame"],"name":"Add Camera Zoom","time":310138.888888889},{"params":[0.05,"camGame"],"time":310185.185185185,"name":"Add Camera Zoom"},{"params":[0.05,"camGame"],"time":310277.777777778,"name":"Add Camera Zoom"},{"params":["img4",""],"name":"HScript Call","time":310277.777777778},{"params":[0.05,"camGame"],"name":"Add Camera Zoom","time":310370.37037037},{"params":[0.05,"camGame"],"name":"Add Camera Zoom","time":310462.962962963},{"params":["img5",""],"name":"HScript Call","time":310462.962962963},{"params":["fuckBitrate",""],"time":310555.555555556,"name":"HScript Call"},{"params":["setGlitchAmt","4.0,0.0,21"],"name":"HScript Call","time":310555.555555556},{"params":[0.05,"camGame"],"name":"Add Camera Zoom","time":310555.555555556},{"params":["hideHud","false,2"],"name":"HScript Call","time":310555.555555556},{"params":[true],"name":"Inverted","time":310555.555555556},{"params":["setGlitchAmt","8,0.0,2"],"name":"HScript Call","time":311111.111111111},{"params":["scream","0.8"],"name":"HScript Call","time":311111.111111111},{"params":["imgS",""],"time":311111.111111111,"name":"HScript Call"},{"params":[true],"time":311111.111111111,"name":"Inverted"},{"params":["scream","0.6"],"name":"HScript Call","time":311388.888888889},{"params":["scream","0.4"],"time":311666.666666667,"name":"HScript Call"},{"params":["hideHud","false,2,0"],"time":311666.666666667,"name":"HScript Call"},{"params":["scream","0.2"],"name":"HScript Call","time":311944.444444444},{"params":["scream","0"],"time":312222.222222222,"name":"HScript Call"},{"params":[0],"name":"Camera Movement","time":328888.888888889},{"params":[1],"name":"Camera Movement","time":331111.111111112}],"scrollSpeed":2.4,"strumLines":[{"strumScale":1,"position":"dad","notes":[{"id":0,"sLen":0,"time":63333.3333333333,"type":0},{"id":3,"sLen":0,"time":63611.1111111111,"type":0},{"id":0,"sLen":0,"time":63888.8888888888,"type":0},{"id":1,"sLen":0,"time":64166.6666666666,"type":0},{"id":1,"sLen":0,"time":64444.4444444444,"type":0},{"id":2,"sLen":0,"time":64722.2222222222,"type":0},{"id":3,"sLen":0,"time":64861.1111111111,"type":0},{"id":0,"sLen":0,"time":65000,"type":0},{"id":2,"sLen":0,"time":65277.7777777777,"type":0},{"id":0,"sLen":0,"time":65555.5555555555,"type":0},{"id":3,"sLen":0,"time":65833.3333333333,"type":0},{"id":2,"sLen":416.666666666672,"time":66111.1111111111,"type":0},{"id":0,"sLen":0,"time":66666.6666666666,"type":0},{"id":1,"sLen":0,"time":66944.4444444444,"type":0},{"id":0,"sLen":0,"time":67222.2222222222,"type":0},{"id":2,"sLen":0,"time":67361.1111111111,"type":0},{"id":1,"sLen":138.888888888891,"time":67500,"type":0},{"id":3,"sLen":138.888888888891,"time":67777.7777777777,"type":0},{"id":2,"sLen":138.888888888891,"time":68055.5555555555,"type":0},{"id":3,"sLen":0,"time":68333.3333333333,"type":0},{"id":1,"sLen":0,"time":68472.2222222222,"type":0},{"id":3,"sLen":0,"time":68611.1111111111,"type":0},{"id":2,"sLen":138.888888888891,"time":68750,"type":0},{"id":1,"sLen":0,"time":69027.7777777777,"type":0},{"id":3,"sLen":0,"time":69166.6666666666,"type":0},{"id":2,"sLen":0,"time":69305.5555555555,"type":0},{"id":0,"sLen":0,"time":69444.4444444444,"type":0},{"id":3,"sLen":0,"time":69583.3333333333,"type":0},{"id":1,"sLen":0,"time":69722.2222222222,"type":0},{"id":2,"sLen":0,"time":69861.1111111111,"type":0},{"id":0,"sLen":0,"time":70000,"type":0},{"id":1,"sLen":0,"time":70277.7777777777,"type":0},{"id":2,"sLen":0,"time":70416.6666666666,"type":0},{"id":0,"sLen":0,"time":70555.5555555555,"type":0},{"id":3,"sLen":0,"time":70694.4444444444,"type":0},{"id":1,"sLen":138.888888888891,"time":70833.3333333333,"type":0},{"id":2,"sLen":138.888888888891,"time":71111.1111111111,"type":0},{"id":0,"sLen":0,"time":71388.8888888888,"type":0},{"id":1,"sLen":0,"time":71527.7777777777,"type":0},{"id":0,"sLen":0,"time":71666.6666666666,"type":0},{"id":2,"sLen":0,"time":71944.4444444444,"type":0},{"id":1,"sLen":0,"time":72083.3333333333,"type":0},{"id":3,"sLen":0,"time":72222.2222222222,"type":0},{"id":0,"sLen":0,"time":72361.1111111111,"type":0},{"id":2,"sLen":0,"time":72500,"type":0},{"id":3,"sLen":0,"time":72638.8888888888,"type":0},{"id":2,"sLen":0,"time":72777.7777777777,"type":0},{"id":1,"sLen":0,"time":72916.6666666666,"type":0},{"id":3,"sLen":0,"time":73055.5555555555,"type":0},{"id":0,"sLen":0,"time":73194.4444444444,"type":0},{"id":2,"sLen":0,"time":73333.3333333333,"type":0},{"id":1,"sLen":0,"time":73472.2222222222,"type":0},{"id":0,"sLen":0,"time":73611.1111111111,"type":0},{"id":1,"sLen":0,"time":73750,"type":0},{"id":3,"sLen":0,"time":73888.8888888888,"type":0},{"id":1,"sLen":0,"time":74027.7777777777,"type":0},{"id":2,"sLen":0,"time":74166.6666666666,"type":0},{"id":0,"sLen":0,"time":74305.5555555555,"type":0},{"id":1,"sLen":0,"time":74444.4444444444,"type":0},{"id":3,"sLen":0,"time":74583.3333333333,"type":0},{"id":0,"sLen":0,"time":74722.2222222222,"type":0},{"id":2,"sLen":0,"time":74861.1111111111,"type":0},{"id":1,"sLen":0,"time":75000,"type":0},{"id":3,"sLen":0,"time":75138.8888888888,"type":0},{"id":2,"sLen":0,"time":75277.7777777777,"type":0},{"id":3,"sLen":0,"time":75416.6666666666,"type":0},{"id":0,"sLen":0,"time":75555.5555555555,"type":0},{"id":3,"sLen":0,"time":75694.4444444444,"type":0},{"id":1,"sLen":0,"time":75833.3333333333,"type":0},{"id":2,"sLen":0,"time":75972.2222222222,"type":0},{"id":0,"sLen":0,"time":76111.1111111111,"type":0},{"id":1,"sLen":0,"time":76250,"type":0},{"id":0,"sLen":0,"time":76388.8888888888,"type":0},{"id":3,"sLen":0,"time":76527.7777777777,"type":0},{"id":2,"sLen":138.888888888891,"time":76666.6666666666,"type":0},{"id":3,"sLen":138.888888888891,"time":77222.2222222222,"type":0},{"id":1,"sLen":0,"time":77499.9999999999,"type":0},{"id":1,"sLen":0,"time":78055.5555555555,"type":0},{"id":0,"sLen":0,"time":78194.4444444444,"type":0},{"id":2,"sLen":138.888888888891,"time":78333.3333333333,"type":0},{"id":3,"sLen":0,"time":78888.8888888888,"type":0},{"id":3,"sLen":0,"time":79166.6666666666,"type":0},{"id":0,"sLen":0,"time":79722.2222222222,"type":0},{"id":1,"sLen":0,"time":79861.1111111111,"type":0},{"id":2,"sLen":138.888888888891,"time":79999.9999999999,"type":0},{"id":0,"sLen":0,"time":80555.5555555555,"type":0},{"id":2,"sLen":0,"time":80694.4444444444,"type":0},{"id":1,"sLen":138.888888888891,"time":80833.3333333333,"type":0},{"id":0,"sLen":0,"time":81388.8888888888,"type":0},{"id":3,"sLen":0,"time":81527.7777777777,"type":0},{"id":2,"sLen":0,"time":81666.6666666666,"type":0},{"id":0,"sLen":0,"time":81805.5555555555,"type":0},{"id":2,"sLen":0,"time":81944.4444444444,"type":0},{"id":3,"sLen":0,"time":82083.3333333333,"type":0},{"id":1,"sLen":138.888888888891,"time":82222.2222222222,"type":0},{"id":2,"sLen":277.777777777781,"time":82499.9999999999,"type":0},{"id":3,"sLen":0,"time":82916.6666666666,"type":0},{"id":1,"sLen":694.444444444438,"time":83333.3333333333,"type":0},{"id":0,"sLen":694.444444444438,"time":84166.6666666666,"type":0},{"id":2,"sLen":416.666666666672,"time":84999.9999999999,"type":0},{"id":3,"sLen":277.777777777781,"time":85833.3333333333,"type":0},{"id":0,"sLen":0,"time":86388.8888888888,"type":0},{"id":2,"sLen":0,"time":86527.7777777777,"type":0},{"id":1,"sLen":833.333333333343,"time":86666.6666666666,"type":0},{"id":2,"sLen":416.666666666672,"time":89999.9999999999,"type":0},{"id":3,"sLen":0,"time":90555.5555555555,"type":0},{"id":0,"sLen":0,"time":90694.4444444444,"type":0},{"id":3,"sLen":416.666666666672,"time":90833.3333333333,"type":0},{"id":2,"sLen":0,"time":91388.8888888888,"type":0},{"id":1,"sLen":0,"time":91527.7777777777,"type":0},{"id":2,"sLen":416.666666666672,"time":91666.6666666666,"type":0},{"id":3,"sLen":0,"time":92222.2222222221,"type":0},{"id":1,"sLen":0,"time":92361.111111111,"type":0},{"id":2,"sLen":416.666666666672,"time":92499.9999999999,"type":0},{"id":3,"sLen":0,"time":93055.5555555555,"type":0},{"id":2,"sLen":0,"time":93194.4444444444,"type":0},{"id":1,"sLen":416.666666666672,"time":93333.3333333333,"type":0},{"id":0,"sLen":0,"time":93888.8888888888,"type":0},{"id":1,"sLen":0,"time":94027.7777777777,"type":0},{"id":0,"sLen":416.666666666672,"time":94166.6666666666,"type":0},{"id":2,"sLen":0,"time":94722.2222222221,"type":0},{"id":3,"sLen":0,"time":94861.111111111,"type":0},{"id":2,"sLen":416.666666666672,"time":94999.9999999999,"type":0},{"id":3,"sLen":0,"time":95555.5555555555,"type":0},{"id":1,"sLen":0,"time":95694.4444444444,"type":0},{"id":2,"sLen":416.666666666672,"time":95833.3333333333,"type":0},{"id":3,"sLen":0,"time":96388.8888888888,"type":0},{"id":1,"sLen":0,"time":96527.7777777777,"type":0},{"id":0,"sLen":138.888888888891,"time":96666.6666666666,"type":0},{"id":2,"sLen":208.333333333328,"time":96944.4444444444,"type":0},{"id":1,"sLen":69.444444444438,"time":97291.6666666666,"type":0},{"id":3,"sLen":138.888888888891,"time":97499.9999999999,"type":0},{"id":2,"sLen":208.333333333343,"time":97777.7777777777,"type":0},{"id":0,"sLen":69.444444444438,"time":98124.9999999999,"type":0},{"id":1,"sLen":138.888888888891,"time":98333.3333333333,"type":0},{"id":2,"sLen":208.333333333328,"time":98611.111111111,"type":0},{"id":0,"sLen":69.444444444438,"time":98958.3333333332,"type":0},{"id":3,"sLen":138.888888888891,"time":99166.6666666666,"type":0},{"id":1,"sLen":138.888888888891,"time":99444.4444444444,"type":0},{"id":0,"sLen":138.888888888891,"time":99722.2222222221,"type":0},{"id":3,"sLen":138.888888888891,"time":99999.9999999999,"type":0},{"id":2,"sLen":208.333333333328,"time":100277.777777778,"type":0},{"id":1,"sLen":69.444444444438,"time":100625,"type":0},{"id":3,"sLen":138.888888888891,"time":100833.333333333,"type":0},{"id":2,"sLen":208.333333333328,"time":101111.111111111,"type":0},{"id":1,"sLen":69.444444444438,"time":101458.333333333,"type":0},{"id":3,"sLen":138.888888888891,"time":101666.666666667,"type":0},{"id":2,"sLen":208.333333333328,"time":101944.444444444,"type":0},{"id":0,"sLen":69.444444444438,"time":102291.666666667,"type":0},{"id":1,"sLen":416.666666666672,"time":102500,"type":0},{"id":3,"sLen":0,"time":103055.555555555,"type":0},{"id":0,"sLen":0,"time":103194.444444444,"type":0},{"id":2,"sLen":1388.88888888889,"time":103333.333333333,"type":0},{"id":1,"sLen":694.444444444438,"time":105000,"type":0},{"id":3,"sLen":694.444444444438,"time":105833.333333333,"type":0},{"id":0,"sLen":0,"time":106666.666666667,"type":0},{"id":1,"sLen":0,"time":106805.555555555,"type":0},{"id":0,"sLen":972.222222222219,"time":106944.444444444,"type":0},{"id":2,"sLen":694.444444444438,"time":108333.333333333,"type":0},{"id":3,"sLen":694.444444444438,"time":109166.666666667,"type":0},{"id":1,"sLen":138.888888888891,"time":109722.222222222,"type":0},{"id":2,"sLen":1111.11111111111,"time":110000,"type":0},{"id":1,"sLen":138.888888888891,"time":111388.888888889,"type":0},{"id":0,"sLen":416.666666666672,"time":111666.666666667,"type":0},{"id":2,"sLen":416.666666666672,"time":111944.444444444,"type":0},{"id":1,"sLen":694.444444444438,"time":112500,"type":0},{"id":3,"sLen":138.888888888891,"time":113055.555555555,"type":0},{"id":0,"sLen":1388.88888888889,"time":113333.333333333,"type":0},{"id":2,"sLen":0,"time":120000,"type":0},{"id":3,"sLen":0,"time":120000,"type":0},{"id":1,"sLen":0,"time":120138.888888889,"type":0},{"id":2,"sLen":0,"time":120277.777777778,"type":0},{"id":0,"sLen":0,"time":120416.666666667,"type":0},{"id":2,"sLen":0,"time":120555.555555555,"type":0},{"id":3,"sLen":0,"time":120555.555555555,"type":0},{"id":1,"sLen":277.777777777781,"time":120694.444444444,"type":0},{"id":1,"sLen":0,"time":122222.222222222,"type":0},{"id":3,"sLen":0,"time":122222.222222222,"type":0},{"id":2,"sLen":0,"time":122361.111111111,"type":0},{"id":1,"sLen":0,"time":122500,"type":0},{"id":3,"sLen":0,"time":122638.888888889,"type":0},{"id":0,"sLen":0,"time":122777.777777778,"type":0},{"id":1,"sLen":0,"time":122777.777777778,"type":0},{"id":2,"sLen":277.777777777781,"time":122916.666666667,"type":0},{"id":0,"sLen":0,"time":124444.444444444,"type":0},{"id":1,"sLen":0,"time":124444.444444444,"type":0},{"id":2,"sLen":0,"time":124583.333333333,"type":0},{"id":1,"sLen":0,"time":124722.222222222,"type":0},{"id":0,"sLen":0,"time":124861.111111111,"type":0},{"id":1,"sLen":0,"time":125000,"type":0},{"id":2,"sLen":0,"time":125000,"type":0},{"id":3,"sLen":277.777777777766,"time":125138.888888889,"type":0},{"id":0,"sLen":0,"time":126666.666666667,"type":0},{"id":1,"sLen":0,"time":126666.666666667,"type":0},{"id":2,"sLen":0,"time":126805.555555555,"type":0},{"id":1,"sLen":0,"time":126944.444444444,"type":0},{"id":3,"sLen":0,"time":127083.333333333,"type":0},{"id":0,"sLen":0,"time":127222.222222222,"type":0},{"id":2,"sLen":138.888888888891,"time":127222.222222222,"type":0},{"id":1,"sLen":0,"time":127500,"type":0},{"id":3,"sLen":1111.11111111111,"time":127638.888888889,"type":0},{"id":0,"sLen":0,"time":129861.111111111,"type":0},{"id":2,"sLen":277.777777777781,"time":130000,"type":0},{"id":1,"sLen":0,"time":130416.666666667,"type":0},{"id":3,"sLen":0,"time":130555.555555555,"type":0},{"id":0,"sLen":0,"time":130694.444444444,"type":0},{"id":2,"sLen":0,"time":130833.333333333,"type":0},{"id":1,"sLen":555.555555555547,"time":130972.222222222,"type":0},{"id":0,"sLen":0,"time":132083.333333333,"type":0},{"id":2,"sLen":0,"time":132222.222222222,"type":0},{"id":3,"sLen":0,"time":132500,"type":0},{"id":0,"sLen":0,"time":132638.888888889,"type":0},{"id":1,"sLen":0,"time":132916.666666667,"type":0},{"id":1,"sLen":138.888888888876,"time":133194.444444444,"type":0},{"id":3,"sLen":0,"time":133472.222222222,"type":0},{"id":2,"sLen":416.666666666657,"time":133611.111111111,"type":0},{"id":0,"sLen":0,"time":134305.555555555,"type":0},{"id":2,"sLen":138.888888888876,"time":134444.444444444,"type":0},{"id":3,"sLen":0,"time":134722.222222222,"type":0},{"id":0,"sLen":277.777777777781,"time":134861.111111111,"type":0},{"id":1,"sLen":0,"time":135277.777777778,"type":0},{"id":3,"sLen":138.888888888876,"time":135555.555555555,"type":0},{"id":2,"sLen":138.888888888876,"time":136111.111111111,"type":0},{"id":1,"sLen":0,"time":136388.888888889,"type":0},{"id":3,"sLen":833.333333333343,"time":136527.777777778,"type":0},{"id":0,"sLen":0,"time":137500,"type":0},{"id":2,"sLen":0,"time":173611.111111111,"type":0},{"id":1,"sLen":0,"time":173750,"type":0},{"id":3,"sLen":0,"time":173888.888888889,"type":0},{"id":1,"sLen":0,"time":174027.777777778,"type":0},{"id":2,"sLen":138.888888888876,"time":174305.555555555,"type":0},{"id":1,"sLen":0,"time":174583.333333333,"type":0},{"id":3,"sLen":0,"time":174722.222222222,"type":0},{"id":0,"sLen":0,"time":174861.111111111,"type":0},{"id":2,"sLen":0,"time":175000,"type":0},{"id":0,"sLen":0,"time":175138.888888889,"type":0},{"id":3,"sLen":0,"time":175277.777777778,"type":0},{"id":2,"sLen":138.888888888847,"time":175416.666666667,"type":0},{"id":1,"sLen":0,"time":175694.444444444,"type":0},{"id":2,"sLen":0,"time":175833.333333333,"type":0},{"id":0,"sLen":0,"time":175972.222222222,"type":0},{"id":1,"sLen":0,"time":176111.111111111,"type":0},{"id":2,"sLen":0,"time":176250,"type":0},{"id":0,"sLen":0,"time":176388.888888889,"type":0},{"id":1,"sLen":0,"time":176527.777777778,"type":0},{"id":3,"sLen":0,"time":176666.666666667,"type":0},{"id":0,"sLen":0,"time":176805.555555555,"type":0},{"id":2,"sLen":0,"time":176944.444444444,"type":0},{"id":3,"sLen":0,"time":177083.333333333,"type":0},{"id":2,"sLen":0,"time":177222.222222222,"type":0},{"id":0,"sLen":0,"time":177361.111111111,"type":0},{"id":3,"sLen":0,"time":177500,"type":0},{"id":2,"sLen":0,"time":177638.888888889,"type":0},{"id":1,"sLen":0,"time":177916.666666667,"type":0},{"id":2,"sLen":0,"time":178194.444444444,"type":0},{"id":1,"sLen":0,"time":178333.333333333,"type":0},{"id":3,"sLen":0,"time":178472.222222222,"type":0},{"id":2,"sLen":0,"time":178611.111111111,"type":0},{"id":0,"sLen":0,"time":178750,"type":0},{"id":3,"sLen":0,"time":178796.296296296,"type":0},{"id":1,"sLen":138.888888888876,"time":178888.888888889,"type":0},{"id":2,"sLen":0,"time":179027.777777778,"type":0},{"id":0,"sLen":138.888888888847,"time":179166.666666667,"type":0},{"id":2,"sLen":0,"time":179305.555555555,"type":0},{"id":1,"sLen":0,"time":179444.444444444,"type":0},{"id":3,"sLen":0,"time":179583.333333333,"type":0},{"id":2,"sLen":0,"time":179722.222222222,"type":0},{"id":1,"sLen":138.888888888876,"time":179861.111111111,"type":0},{"id":2,"sLen":0,"time":180138.888888889,"type":0},{"id":1,"sLen":0,"time":180277.777777778,"type":0},{"id":0,"sLen":0,"time":180416.666666667,"type":0},{"id":1,"sLen":0,"time":180625,"type":0},{"id":2,"sLen":0,"time":180694.444444444,"type":0},{"id":0,"sLen":0,"time":180833.333333333,"type":0},{"id":1,"sLen":0,"time":180972.222222222,"type":0},{"id":0,"sLen":0,"time":181180.555555555,"type":0},{"id":2,"sLen":138.888888888876,"time":181250,"type":0},{"id":1,"sLen":0,"time":181527.777777778,"type":0},{"id":0,"sLen":0,"time":181666.666666667,"type":0},{"id":3,"sLen":0,"time":181805.555555555,"type":0},{"id":1,"sLen":0,"time":181944.444444444,"type":0},{"id":0,"sLen":0,"time":182083.333333333,"type":0},{"id":2,"sLen":972.222222222219,"time":182222.222222222,"type":0},{"id":3,"sLen":0,"time":183333.333333333,"type":0},{"id":0,"sLen":138.888888888876,"time":183472.222222222,"type":0},{"id":2,"sLen":555.555555555562,"time":183750,"type":0},{"id":1,"sLen":138.888888888876,"time":184444.444444444,"type":0},{"id":3,"sLen":416.666666666657,"time":184722.222222222,"type":0},{"id":1,"sLen":0,"time":185138.888888889,"type":0},{"id":2,"sLen":0,"time":185277.777777778,"type":0},{"id":0,"sLen":0,"time":185416.666666667,"type":0},{"id":2,"sLen":416.666666666686,"time":185555.555555555,"type":0},{"id":1,"sLen":416.666666666657,"time":186111.111111111,"type":0},{"id":1,"sLen":0,"time":186666.666666667,"type":0},{"id":0,"sLen":0,"time":186805.555555555,"type":0},{"id":1,"sLen":0,"time":186944.444444444,"type":0},{"id":3,"sLen":0,"time":187083.333333333,"type":0},{"id":1,"sLen":0,"time":187222.222222222,"type":0},{"id":0,"sLen":0,"time":187361.111111111,"type":0},{"id":3,"sLen":0,"time":187500,"type":0},{"id":2,"sLen":0,"time":187638.888888889,"type":0},{"id":3,"sLen":0,"time":187777.777777778,"type":0},{"id":1,"sLen":0,"time":187916.666666667,"type":0},{"id":2,"sLen":0,"time":188055.555555555,"type":0},{"id":0,"sLen":0,"time":188194.444444444,"type":0},{"id":1,"sLen":0,"time":188333.333333333,"type":0},{"id":3,"sLen":0,"time":188472.222222222,"type":0},{"id":2,"sLen":0,"time":188611.111111111,"type":0},{"id":0,"sLen":0,"time":188750,"type":0},{"id":3,"sLen":0,"time":188888.888888889,"type":0},{"id":1,"sLen":0,"time":189027.777777778,"type":0},{"id":2,"sLen":0,"time":189166.666666667,"type":0},{"id":0,"sLen":0,"time":189305.555555555,"type":0},{"id":3,"sLen":0,"time":189444.444444444,"type":0},{"id":1,"sLen":0,"time":189583.333333333,"type":0},{"id":0,"sLen":0,"time":189722.222222222,"type":0},{"id":2,"sLen":0,"time":189861.111111111,"type":0},{"id":1,"sLen":0,"time":190000,"type":0},{"id":0,"sLen":0,"time":190138.888888889,"type":0},{"id":2,"sLen":0,"time":190277.777777778,"type":0},{"id":3,"sLen":0,"time":190416.666666667,"type":0},{"id":2,"sLen":0,"time":190555.555555555,"type":0},{"id":1,"sLen":0,"time":190694.444444444,"type":0},{"id":3,"sLen":0,"time":190833.333333333,"type":0},{"id":0,"sLen":0,"time":190972.222222222,"type":0},{"id":2,"sLen":138.888888888876,"time":191388.888888889,"type":0},{"id":1,"sLen":138.888888888847,"time":191666.666666667,"type":0},{"id":3,"sLen":0,"time":191944.444444444,"type":0},{"id":0,"sLen":0,"time":192083.333333333,"type":0},{"id":3,"sLen":0,"time":192222.222222222,"type":0},{"id":2,"sLen":0,"time":192361.111111111,"type":0},{"id":1,"sLen":0,"time":192500,"type":0},{"id":3,"sLen":0,"time":192638.888888889,"type":0},{"id":2,"sLen":0,"time":192777.777777778,"type":0},{"id":0,"sLen":0,"time":192916.666666667,"type":0},{"id":3,"sLen":0,"time":193055.555555555,"type":0},{"id":1,"sLen":0,"time":193194.444444444,"type":0},{"id":3,"sLen":0,"time":193333.333333333,"type":0},{"id":0,"sLen":0,"time":193472.222222222,"type":0},{"id":2,"sLen":0,"time":193611.111111111,"type":0},{"id":1,"sLen":138.888888888876,"time":193750,"type":0},{"id":2,"sLen":0,"time":194027.777777778,"type":0},{"id":3,"sLen":0,"time":194166.666666667,"type":0},{"id":0,"sLen":0,"time":194305.555555555,"type":0},{"id":2,"sLen":0,"time":194444.444444444,"type":0},{"id":1,"sLen":0,"time":194583.333333333,"type":0},{"id":0,"sLen":0,"time":194722.222222222,"type":0},{"id":2,"sLen":138.888888888876,"time":194861.111111111,"type":0},{"id":1,"sLen":0,"time":195138.888888889,"type":0},{"id":3,"sLen":0,"time":195277.777777778,"type":0},{"id":0,"sLen":0,"time":195416.666666667,"type":0},{"id":2,"sLen":0,"time":195555.555555555,"type":0},{"id":0,"sLen":0,"time":195694.444444444,"type":0},{"id":1,"sLen":0,"time":195833.333333333,"type":0},{"id":2,"sLen":138.888888888876,"time":195972.222222222,"type":0},{"id":0,"sLen":0,"time":196250,"type":0},{"id":3,"sLen":0,"time":196388.888888889,"type":0},{"id":2,"sLen":0,"time":196527.777777778,"type":0},{"id":3,"sLen":138.888888888847,"time":196666.666666667,"type":0},{"id":1,"sLen":0,"time":196944.444444444,"type":0},{"id":2,"sLen":138.888888888876,"time":197222.222222222,"type":0},{"id":0,"sLen":138.888888888876,"time":197500,"type":0},{"id":3,"sLen":138.888888888876,"time":197777.777777778,"type":0},{"id":0,"sLen":277.777777777781,"time":198194.444444444,"type":0},{"id":1,"sLen":138.888888888876,"time":198611.111111111,"type":0},{"id":2,"sLen":138.888888888876,"time":198888.888888889,"type":0},{"id":3,"sLen":138.888888888876,"time":199305.555555555,"type":0},{"id":2,"sLen":138.888888888876,"time":199722.222222222,"type":0},{"id":0,"sLen":1250,"time":199861.111111111,"type":0},{"id":2,"sLen":138.888888888876,"time":203611.111111111,"type":0},{"id":1,"sLen":138.888888888876,"time":203888.888888889,"type":0},{"id":3,"sLen":138.888888888876,"time":204166.666666666,"type":0},{"id":2,"sLen":277.777777777781,"time":204444.444444444,"type":0},{"id":1,"sLen":138.888888888847,"time":204861.111111111,"type":0},{"id":3,"sLen":555.555555555562,"time":205138.888888889,"type":0},{"id":1,"sLen":0,"time":205833.333333333,"type":0},{"id":0,"sLen":0,"time":205972.222222222,"type":0},{"id":1,"sLen":0,"time":206111.111111111,"type":0},{"id":2,"sLen":972.222222222219,"time":206666.666666666,"type":0},{"id":0,"sLen":416.666666666657,"time":207777.777777778,"type":0},{"id":2,"sLen":416.666666666657,"time":208333.333333333,"type":0},{"id":1,"sLen":138.888888888876,"time":208888.888888889,"type":0},{"id":3,"sLen":0,"time":208888.888888889,"type":0},{"id":0,"sLen":138.888888888876,"time":209166.666666666,"type":0},{"id":3,"sLen":138.888888888876,"time":209444.444444444,"type":0},{"id":0,"sLen":0,"time":209722.222222222,"type":0},{"id":3,"sLen":277.777777777781,"time":209861.111111111,"type":0},{"id":1,"sLen":0,"time":210277.777777778,"type":0},{"id":0,"sLen":0,"time":210416.666666666,"type":0},{"id":2,"sLen":0,"time":210555.555555555,"type":0},{"id":1,"sLen":0,"time":210694.444444444,"type":0},{"id":2,"sLen":0,"time":210833.333333333,"type":0},{"id":0,"sLen":138.888888888876,"time":210972.222222222,"type":0},{"id":1,"sLen":0,"time":211250,"type":0},{"id":2,"sLen":0,"time":211388.888888889,"type":0},{"id":1,"sLen":0,"time":211527.777777778,"type":0},{"id":2,"sLen":0,"time":211666.666666666,"type":0},{"id":0,"sLen":0,"time":211805.555555555,"type":0},{"id":3,"sLen":0,"time":211944.444444444,"type":0},{"id":2,"sLen":138.888888888876,"time":212083.333333333,"type":0},{"id":1,"sLen":0,"time":212361.111111111,"type":0},{"id":0,"sLen":0,"time":212500,"type":0},{"id":3,"sLen":0,"time":212638.888888889,"type":0},{"id":1,"sLen":0,"time":212777.777777778,"type":0},{"id":3,"sLen":0,"time":212916.666666666,"type":0},{"id":2,"sLen":0,"time":213055.555555555,"type":0},{"id":0,"sLen":138.888888888876,"time":213194.444444444,"type":0},{"id":1,"sLen":0,"time":213333.333333333,"type":0},{"id":2,"sLen":0,"time":213472.222222222,"type":0},{"id":0,"sLen":138.888888888847,"time":213611.111111111,"type":0},{"id":1,"sLen":0,"time":213750,"type":0},{"id":2,"sLen":0,"time":213888.888888889,"type":0},{"id":0,"sLen":0,"time":214027.777777778,"type":0},{"id":2,"sLen":0,"time":214166.666666666,"type":0},{"id":3,"sLen":138.888888888876,"time":214305.555555555,"type":0},{"id":2,"sLen":0,"time":214583.333333333,"type":0},{"id":1,"sLen":0,"time":214722.222222222,"type":0},{"id":2,"sLen":0,"time":214861.111111111,"type":0},{"id":0,"sLen":138.888888888876,"time":215000,"type":0},{"id":3,"sLen":0,"time":215138.888888889,"type":0},{"id":2,"sLen":138.888888888876,"time":215277.777777778,"type":0},{"id":1,"sLen":972.222222222219,"time":215555.555555555,"type":0},{"id":3,"sLen":416.666666666657,"time":216666.666666666,"type":0},{"id":0,"sLen":416.666666666657,"time":217222.222222222,"type":0},{"id":2,"sLen":972.222222222219,"time":228888.888888889,"type":0},{"id":0,"sLen":972.222222222219,"time":230000,"type":0},{"id":3,"sLen":138.888888888847,"time":231388.888888889,"type":0},{"id":1,"sLen":0,"time":231666.666666666,"type":0},{"id":2,"sLen":416.666666666599,"time":231944.444444444,"type":0},{"id":3,"sLen":138.888888888905,"time":232500,"type":0},{"id":1,"sLen":0,"time":232777.777777778,"type":0},{"id":2,"sLen":416.666666666599,"time":233055.555555555,"type":0},{"id":3,"sLen":138.888888888905,"time":233611.111111111,"type":0},{"id":2,"sLen":0,"time":233888.888888889,"type":0},{"id":1,"sLen":416.666666666657,"time":234166.666666666,"type":0},{"id":2,"sLen":138.888888888905,"time":234722.222222222,"type":0},{"id":0,"sLen":0,"time":235000,"type":0},{"id":2,"sLen":0,"time":235277.777777778,"type":0},{"id":1,"sLen":0,"time":235416.666666666,"type":0},{"id":2,"sLen":0,"time":235694.444444444,"type":0},{"id":1,"sLen":0,"time":235833.333333333,"type":0},{"id":0,"sLen":0,"time":236250,"type":0},{"id":2,"sLen":0,"time":236388.888888889,"type":0},{"id":1,"sLen":0,"time":236527.777777778,"type":0},{"id":2,"sLen":0,"time":236805.555555555,"type":0},{"id":1,"sLen":0,"time":236944.444444444,"type":0},{"id":3,"sLen":0,"time":237222.222222222,"type":0},{"id":2,"sLen":138.888888888905,"time":237361.111111111,"type":0},{"id":1,"sLen":0,"time":237638.888888889,"type":0},{"id":3,"sLen":972.222222222219,"time":237777.777777778,"type":0},{"id":1,"sLen":972.22222222219,"time":238888.888888889,"type":0},{"id":2,"sLen":0,"time":240000,"type":0},{"id":0,"sLen":138.888888888876,"time":240277.777777778,"type":0},{"id":1,"sLen":0,"time":240555.555555555,"type":0},{"id":2,"sLen":138.888888888847,"time":240833.333333333,"type":0},{"id":0,"sLen":0,"time":241111.111111111,"type":0},{"id":2,"sLen":0,"time":241319.444444444,"type":0},{"id":1,"sLen":138.888888888847,"time":241388.888888889,"type":0},{"id":3,"sLen":0,"time":241666.666666666,"type":0},{"id":2,"sLen":416.666666666657,"time":241944.444444444,"type":0},{"id":0,"sLen":0,"time":242500,"type":0},{"id":1,"sLen":0,"time":242777.777777778,"type":0},{"id":2,"sLen":416.666666666599,"time":243055.555555555,"type":0},{"id":0,"sLen":0,"time":243611.111111111,"type":0},{"id":3,"sLen":0,"time":243750,"type":0},{"id":2,"sLen":0,"time":244027.777777778,"type":0},{"id":0,"sLen":0,"time":244166.666666666,"type":0},{"id":1,"sLen":277.777777777752,"time":244305.555555555,"type":0},{"id":3,"sLen":138.888888888905,"time":244722.222222222,"type":0},{"id":2,"sLen":138.888888888905,"time":245000,"type":0},{"id":0,"sLen":0,"time":245277.777777778,"type":0},{"id":1,"sLen":277.777777777781,"time":245416.666666666,"type":0},{"id":2,"sLen":138.888888888905,"time":245833.333333333,"type":0},{"id":0,"sLen":138.888888888905,"time":246111.111111111,"type":0},{"id":2,"sLen":0,"time":246388.888888889,"type":0},{"id":3,"sLen":277.777777777781,"time":246527.777777778,"type":0},{"id":1,"sLen":277.777777777781,"time":246944.444444444,"type":0},{"id":2,"sLen":277.777777777839,"time":247361.111111111,"type":0},{"id":0,"sLen":416.666666666657,"time":247777.777777778,"type":0},{"id":2,"sLen":416.666666666686,"time":248333.333333333,"type":0},{"id":1,"sLen":138.888888888847,"time":248888.888888889,"type":0},{"id":2,"sLen":138.888888888876,"time":249166.666666666,"type":0},{"id":0,"sLen":0,"time":249444.444444444,"type":0},{"id":3,"sLen":0,"time":249722.222222222,"type":0},{"id":0,"sLen":0,"time":249861.111111111,"type":0},{"id":2,"sLen":0,"time":250138.888888889,"type":0},{"id":1,"sLen":0,"time":250416.666666666,"type":0},{"id":1,"sLen":0,"time":250694.444444444,"type":0},{"id":2,"sLen":0,"time":250833.333333333,"type":0},{"id":3,"sLen":0,"time":250972.222222222,"type":0},{"id":0,"sLen":0,"time":251111.111111111,"type":0},{"id":2,"sLen":0,"time":251250,"type":0},{"id":1,"sLen":0,"time":251388.888888889,"type":0},{"id":3,"sLen":0,"time":251527.777777778,"type":0},{"id":2,"sLen":138.888888888876,"time":251666.666666666,"type":0},{"id":0,"sLen":0,"time":251944.444444444,"type":0},{"id":2,"sLen":0,"time":252083.333333333,"type":0},{"id":0,"sLen":0,"time":252222.222222222,"type":0},{"id":1,"sLen":0,"time":252361.111111111,"type":0},{"id":2,"sLen":0,"time":252500,"type":0},{"id":0,"sLen":0,"time":252638.888888889,"type":0},{"id":3,"sLen":0,"time":252916.666666666,"type":0},{"id":2,"sLen":0,"time":253055.555555555,"type":0},{"id":1,"sLen":0,"time":253194.444444444,"type":0},{"id":2,"sLen":0,"time":253333.333333333,"type":0},{"id":3,"sLen":0,"time":253611.111111111,"type":0},{"id":1,"sLen":0,"time":253750,"type":0},{"id":2,"sLen":0,"time":254027.777777778,"type":0},{"id":0,"sLen":0,"time":254166.666666666,"type":0},{"id":1,"sLen":0,"time":254305.555555555,"type":0},{"id":3,"sLen":0,"time":254444.444444444,"type":0},{"id":0,"sLen":0,"time":254583.333333333,"type":0},{"id":2,"sLen":138.888888888905,"time":254722.222222222,"type":0},{"id":1,"sLen":138.888888888847,"time":255000,"type":0},{"id":0,"sLen":0,"time":255277.777777778,"type":0},{"id":3,"sLen":0,"time":255416.666666666,"type":0},{"id":2,"sLen":0,"time":255555.555555555,"type":0},{"id":1,"sLen":0,"time":255694.444444444,"type":0},{"id":2,"sLen":0,"time":255833.333333333,"type":0},{"id":0,"sLen":0,"time":256111.111111111,"type":0},{"id":2,"sLen":416.666666667646,"time":256388.888888889,"type":0},{"id":3,"sLen":138.888888888847,"time":256944.444444444,"type":0},{"id":1,"sLen":416.666666666686,"time":257222.222222222,"type":0},{"id":0,"sLen":138.888888888876,"time":257777.777777778,"type":0},{"id":3,"sLen":138.888888888818,"time":258055.555555555,"type":0},{"id":2,"sLen":138.888888888905,"time":258333.333333333,"type":0},{"id":1,"sLen":0,"time":258611.111111111,"type":0},{"id":2,"sLen":0,"time":258750,"type":0},{"id":0,"sLen":0,"time":259027.777777778,"type":0},{"id":3,"sLen":0,"time":259305.555555555,"type":0},{"id":0,"sLen":0,"time":259583.333333333,"type":0},{"id":1,"sLen":0,"time":259722.222222222,"type":0},{"id":3,"sLen":0,"time":259861.111111111,"type":0},{"id":2,"sLen":138.888888888847,"time":260000,"type":0},{"id":1,"sLen":0,"time":260277.777777778,"type":0},{"id":3,"sLen":138.888888888876,"time":260416.666666666,"type":0},{"id":1,"sLen":0,"time":260694.444444444,"type":0},{"id":2,"sLen":0,"time":260833.333333333,"type":0},{"id":0,"sLen":0,"time":260972.222222222,"type":0},{"id":1,"sLen":138.888888888934,"time":261111.111111111,"type":0},{"id":0,"sLen":0,"time":261388.888888889,"type":0},{"id":2,"sLen":0,"time":261527.777777778,"type":0},{"id":1,"sLen":0,"time":261805.555555555,"type":0},{"id":3,"sLen":0,"time":261944.444444444,"type":0},{"id":0,"sLen":0,"time":262083.333333333,"type":0},{"id":2,"sLen":138.888888888876,"time":262222.222222222,"type":0},{"id":1,"sLen":1250,"time":262500,"type":0},{"id":2,"sLen":138.888888888876,"time":266666.666666666,"type":0},{"id":1,"sLen":0,"time":266944.444444444,"type":0},{"id":2,"sLen":138.888888888876,"time":267083.333333333,"type":0},{"id":1,"sLen":0,"time":267361.111111111,"type":0},{"id":0,"sLen":0,"time":267500,"type":0},{"id":1,"sLen":0,"time":267638.888888889,"type":0},{"id":2,"sLen":0,"time":267777.777777778,"type":0},{"id":0,"sLen":0,"time":268055.555555555,"type":0},{"id":3,"sLen":0,"time":268194.444444444,"type":0},{"id":1,"sLen":0,"time":268472.222222222,"type":0},{"id":2,"sLen":0,"time":268611.111111111,"type":0},{"id":0,"sLen":0,"time":268750,"type":0},{"id":1,"sLen":138.888888888876,"time":268888.888888889,"type":0},{"id":2,"sLen":0,"time":269166.666666666,"type":0},{"id":1,"sLen":138.888888888876,"time":269305.555555555,"type":0},{"id":3,"sLen":0,"time":269583.333333333,"type":0},{"id":0,"sLen":0,"time":269722.222222222,"type":0},{"id":2,"sLen":0,"time":269861.111111111,"type":0},{"id":1,"sLen":0,"time":270000,"type":0},{"id":3,"sLen":0,"time":270416.666666666,"type":0},{"id":0,"sLen":0,"time":270694.444444444,"type":0},{"id":1,"sLen":0,"time":270833.333333333,"type":0},{"id":2,"sLen":0,"time":270972.222222222,"type":0},{"id":2,"sLen":0,"time":272083.333333333,"type":0},{"id":0,"sLen":0,"time":272222.222222222,"type":0},{"id":1,"sLen":0,"time":272361.111111111,"type":0},{"id":3,"sLen":0,"time":272500,"type":0},{"id":2,"sLen":0,"time":272638.888888889,"type":0},{"id":0,"sLen":0,"time":272777.777777778,"type":0},{"id":1,"sLen":0,"time":272916.666666667,"type":0},{"id":3,"sLen":0,"time":273055.555555555,"type":0},{"id":0,"sLen":0,"time":273194.444444444,"type":0},{"id":2,"sLen":0,"time":273750,"type":0},{"id":1,"sLen":0,"time":274027.777777778,"type":0},{"id":3,"sLen":0,"time":274027.777777778,"type":0},{"id":0,"sLen":0,"time":274166.666666667,"type":0},{"id":2,"sLen":0,"time":274166.666666667,"type":0},{"id":0,"sLen":0,"time":274305.555555555,"type":0},{"id":1,"sLen":0,"time":274305.555555555,"type":0},{"id":1,"sLen":0,"time":274444.444444444,"type":0},{"id":2,"sLen":0,"time":274444.444444444,"type":0},{"id":3,"sLen":0,"time":274583.333333333,"type":0},{"id":2,"sLen":0,"time":274722.222222222,"type":0},{"id":0,"sLen":0,"time":274861.111111111,"type":0},{"id":3,"sLen":0,"time":274861.111111111,"type":0},{"id":2,"sLen":0,"time":275000,"type":0},{"id":1,"sLen":0,"time":275138.888888889,"type":0},{"id":3,"sLen":0,"time":275277.777777778,"type":0},{"id":0,"sLen":0,"time":275416.666666667,"type":0},{"id":3,"sLen":0,"time":275555.555555555,"type":0},{"id":1,"sLen":0,"time":275625,"type":0},{"id":2,"sLen":138.888888888876,"time":275625,"type":0},{"id":0,"sLen":0,"time":275833.333333333,"type":0},{"id":3,"sLen":0,"time":276111.111111111,"type":0},{"id":0,"sLen":0,"time":276250,"type":0},{"id":1,"sLen":0,"time":276388.888888889,"type":0},{"id":2,"sLen":138.888888888876,"time":276388.888888889,"type":0},{"id":0,"sLen":0,"time":276666.666666667,"type":0},{"id":3,"sLen":138.888888888876,"time":276666.666666667,"type":0},{"id":1,"sLen":0,"time":276944.444444444,"type":0},{"id":2,"sLen":138.888888888876,"time":276944.444444444,"type":0},{"id":0,"sLen":138.888888888876,"time":277222.222222222,"type":0},{"id":1,"sLen":0,"time":277222.222222222,"type":0},{"id":1,"sLen":138.888888888876,"time":277500,"type":0},{"id":3,"sLen":0,"time":277500,"type":0},{"id":0,"sLen":0,"time":277777.777777778,"type":0},{"id":1,"sLen":0,"time":277847.222222222,"type":0},{"id":2,"sLen":138.888888888876,"time":277847.222222222,"type":0},{"id":3,"sLen":0,"time":278055.555555555,"type":0},{"id":1,"sLen":0,"time":278333.333333333,"type":0},{"id":2,"sLen":0,"time":278333.333333333,"type":0},{"id":0,"sLen":0,"time":278472.222222222,"type":0},{"id":1,"sLen":0,"time":278611.111111111,"type":0},{"id":2,"sLen":0,"time":278888.888888889,"type":0},{"id":3,"sLen":0,"time":278888.888888889,"type":0},{"id":0,"sLen":138.888888888876,"time":279166.666666667,"type":0},{"id":1,"sLen":0,"time":279444.444444444,"type":0},{"id":2,"sLen":138.888888888876,"time":279444.444444444,"type":0},{"id":3,"sLen":0,"time":279722.222222222,"type":0},{"id":1,"sLen":0,"time":280000,"type":0},{"id":0,"sLen":0,"time":280069.444444444,"type":0},{"id":2,"sLen":138.888888888876,"time":280069.444444444,"type":0},{"id":1,"sLen":0,"time":280277.777777778,"type":0},{"id":3,"sLen":0,"time":280555.555555556,"type":0},{"id":0,"sLen":0,"time":280694.444444444,"type":0},{"id":1,"sLen":0,"time":280833.333333333,"type":0},{"id":2,"sLen":138.888888888876,"time":280833.333333333,"type":0},{"id":0,"sLen":0,"time":281111.111111111,"type":0},{"id":3,"sLen":0,"time":281111.111111111,"type":0},{"id":1,"sLen":138.888888888876,"time":281388.888888889,"type":0},{"id":2,"sLen":0,"time":281388.888888889,"type":0},{"id":0,"sLen":138.888888888876,"time":281666.666666667,"type":0},{"id":2,"sLen":0,"time":281666.666666667,"type":0},{"id":1,"sLen":0,"time":281944.444444444,"type":0},{"id":2,"sLen":138.888888888876,"time":281944.444444444,"type":0},{"id":0,"sLen":0,"time":282222.222222222,"type":0},{"id":1,"sLen":138.888888888876,"time":282291.666666667,"type":0},{"id":3,"sLen":0,"time":282291.666666667,"type":0},{"id":2,"sLen":0,"time":282500,"type":0},{"id":0,"sLen":0,"time":282777.777777778,"type":0},{"id":1,"sLen":0,"time":282777.777777778,"type":0},{"id":2,"sLen":0,"time":282916.666666667,"type":0},{"id":3,"sLen":0,"time":283055.555555556,"type":0},{"id":0,"sLen":0,"time":283333.333333333,"type":0},{"id":2,"sLen":138.888888888876,"time":283333.333333333,"type":0},{"id":1,"sLen":0,"time":283611.111111111,"type":0},{"id":3,"sLen":0,"time":283750,"type":0},{"id":0,"sLen":138.888888888876,"time":283888.888888889,"type":0},{"id":2,"sLen":0,"time":283888.888888889,"type":0},{"id":3,"sLen":138.888888888876,"time":284166.666666667,"type":0},{"id":1,"sLen":0,"time":284722.222222222,"type":0},{"id":2,"sLen":138.888888888876,"time":284722.222222222,"type":0},{"id":0,"sLen":138.888888888876,"time":285277.777777778,"type":0},{"id":3,"sLen":0,"time":285277.777777778,"type":0},{"id":1,"sLen":0,"time":285833.333333333,"type":0},{"id":2,"sLen":138.888888888876,"time":285833.333333333,"type":0},{"id":0,"sLen":0,"time":286111.111111111,"type":0},{"id":3,"sLen":0,"time":286111.111111111,"type":0},{"id":1,"sLen":0,"time":286250,"type":0},{"id":2,"sLen":138.888888888876,"time":286250,"type":0},{"id":0,"sLen":0,"time":286527.777777778,"type":0},{"id":3,"sLen":0,"time":286527.777777778,"type":0},{"id":1,"sLen":138.888888888876,"time":286944.444444444,"type":0},{"id":3,"sLen":0,"time":286944.444444444,"type":0},{"id":0,"sLen":0,"time":287500,"type":0},{"id":2,"sLen":138.888888888876,"time":287500,"type":0},{"id":3,"sLen":0,"time":288055.555555555,"type":0},{"id":0,"sLen":0,"time":288194.444444444,"type":0},{"id":3,"sLen":0,"time":288333.333333333,"type":0},{"id":1,"sLen":138.888888889458,"time":288611.111111111,"type":0},{"id":2,"sLen":0,"time":288611.111111111,"type":0},{"id":1,"sLen":0,"time":289166.666666667,"type":0},{"id":3,"sLen":138.888888888876,"time":289166.666666667,"type":0},{"id":0,"sLen":138.888888888876,"time":289722.222222222,"type":0},{"id":2,"sLen":0,"time":289722.222222222,"type":0},{"id":1,"sLen":0,"time":290277.777777778,"type":0},{"id":3,"sLen":138.888888888876,"time":290277.777777778,"type":0},{"id":0,"sLen":0,"time":290555.555555555,"type":0},{"id":2,"sLen":0,"time":290555.555555556,"type":0},{"id":1,"sLen":0,"time":290694.444444444,"type":0},{"id":3,"sLen":138.888888888876,"time":290694.444444444,"type":0},{"id":0,"sLen":0,"time":290972.222222222,"type":0},{"id":2,"sLen":0,"time":290972.222222222,"type":0},{"id":1,"sLen":0,"time":292222.222222222,"type":0},{"id":2,"sLen":416.666666666686,"time":292222.222222222,"type":0},{"id":1,"sLen":138.888888888876,"time":292777.777777778,"type":0},{"id":3,"sLen":138.888888888876,"time":292777.777777778,"type":0},{"id":2,"sLen":0,"time":292916.666666667,"type":0},{"id":0,"sLen":138.888888888876,"time":293055.555555556,"type":0},{"id":3,"sLen":138.888888888876,"time":293055.555555556,"type":0},{"id":2,"sLen":0,"time":293194.444444445,"type":0},{"id":1,"sLen":0,"time":293333.333333333,"type":0},{"id":0,"sLen":0,"time":293402.777777778,"type":0},{"id":2,"sLen":138.888888888876,"time":293402.777777778,"type":0},{"id":1,"sLen":0,"time":293611.111111111,"type":0},{"id":2,"sLen":0,"time":293888.888888889,"type":0},{"id":3,"sLen":0,"time":293888.888888889,"type":0},{"id":0,"sLen":0,"time":294027.777777778,"type":0},{"id":1,"sLen":0,"time":294166.666666667,"type":0},{"id":0,"sLen":0,"time":294444.444444445,"type":0},{"id":2,"sLen":138.888888888876,"time":294444.444444445,"type":0},{"id":3,"sLen":0,"time":294722.222222222,"type":0},{"id":1,"sLen":0,"time":294861.111111111,"type":0},{"id":0,"sLen":0,"time":295000,"type":0},{"id":2,"sLen":138.888888888876,"time":295000,"type":0},{"id":3,"sLen":0,"time":295277.777777778,"type":0},{"id":0,"sLen":0,"time":295416.666666667,"type":0},{"id":2,"sLen":0,"time":295555.555555556,"type":0},{"id":1,"sLen":138.888888888876,"time":295625,"type":0},{"id":3,"sLen":0,"time":295625,"type":0},{"id":2,"sLen":0,"time":295833.333333333,"type":0},{"id":0,"sLen":0,"time":296111.111111111,"type":0},{"id":3,"sLen":0,"time":296250,"type":0},{"id":1,"sLen":0,"time":296388.888888889,"type":0},{"id":2,"sLen":0,"time":296388.888888889,"type":0},{"id":0,"sLen":0,"time":296666.666666667,"type":0},{"id":1,"sLen":0,"time":296944.444444445,"type":0},{"id":2,"sLen":138.888888888876,"time":296944.444444445,"type":0},{"id":1,"sLen":0,"time":297222.222222222,"type":0},{"id":3,"sLen":138.888888888876,"time":297222.222222222,"type":0},{"id":1,"sLen":0,"time":297500,"type":0},{"id":2,"sLen":138.888888888876,"time":297500,"type":0},{"id":0,"sLen":416.666666666686,"time":297777.777777778,"type":0},{"id":2,"sLen":0,"time":298333.333333333,"type":0},{"id":1,"sLen":694.444444445835,"time":298611.111111111,"type":0},{"id":0,"sLen":0,"time":299444.444444445,"type":0},{"id":2,"sLen":0,"time":299722.222222222,"type":0},{"id":1,"sLen":416.666666666686,"time":300000,"type":0},{"id":0,"sLen":416.666666666686,"time":300555.555555556,"type":0},{"id":2,"sLen":416.666666666919,"time":301111.111111111,"type":0},{"id":1,"sLen":416.666666666686,"time":301666.666666667,"type":0},{"id":0,"sLen":0,"time":302500,"type":0},{"id":2,"sLen":138.888888888876,"time":302500,"type":0},{"id":0,"sLen":138.888888888876,"time":303055.555555556,"type":0},{"id":2,"sLen":0,"time":303055.555555556,"type":0},{"id":1,"sLen":138.888888889458,"time":303611.111111111,"type":0},{"id":3,"sLen":0,"time":303611.111111111,"type":0},{"id":0,"sLen":0,"time":303888.888888889,"type":0},{"id":1,"sLen":138.888888888876,"time":304027.777777778,"type":0},{"id":3,"sLen":0,"time":304027.777777778,"type":0},{"id":0,"sLen":0,"time":304305.555555556,"type":0},{"id":1,"sLen":0,"time":304722.222222222,"type":0},{"id":2,"sLen":138.888888888876,"time":304722.222222222,"type":0},{"id":1,"sLen":138.888888888876,"time":305277.777777778,"type":0},{"id":2,"sLen":0,"time":305277.777777778,"type":0},{"id":0,"sLen":0,"time":305833.333333334,"type":0},{"id":3,"sLen":0,"time":305972.222222222,"type":0},{"id":1,"sLen":0,"time":306111.111111111,"type":0},{"id":2,"sLen":0,"time":306111.111111111,"type":0},{"id":0,"sLen":0,"time":306388.888888889,"type":0},{"id":2,"sLen":0,"time":306666.666666667,"type":0},{"id":3,"sLen":0,"time":306666.666666667,"type":0},{"id":0,"sLen":0,"time":306805.555555556,"type":0},{"id":1,"sLen":0,"time":306944.444444445,"type":0},{"id":3,"sLen":0,"time":307083.333333334,"type":0},{"id":0,"sLen":0,"time":307222.222222222,"type":0},{"id":2,"sLen":0,"time":307222.222222222,"type":0},{"id":3,"sLen":0,"time":307361.111111111,"type":0},{"id":1,"sLen":0,"time":307500,"type":0},{"id":0,"sLen":0,"time":307638.888888889,"type":0},{"id":2,"sLen":0,"time":307777.777777778,"type":0},{"id":3,"sLen":0,"time":307777.777777778,"type":0},{"id":1,"sLen":0,"time":307916.666666667,"type":0},{"id":0,"sLen":0,"time":308055.555555556,"type":0},{"id":1,"sLen":0,"time":308194.444444445,"type":0},{"id":2,"sLen":0,"time":308333.333333334,"type":0},{"id":3,"sLen":0,"time":308333.333333334,"type":0},{"id":0,"sLen":0,"time":308472.222222222,"type":0},{"id":1,"sLen":0,"time":308611.111111111,"type":0},{"id":3,"sLen":0,"time":308750,"type":0},{"id":0,"sLen":0,"time":308888.888888889,"type":0},{"id":2,"sLen":0,"time":308888.888888889,"type":0},{"id":1,"sLen":0,"time":309027.777777778,"type":0},{"id":3,"sLen":0,"time":309166.666666667,"type":0},{"id":0,"sLen":0,"time":309305.555555556,"type":0},{"id":1,"sLen":0,"time":309444.444444445,"type":0},{"id":2,"sLen":0,"time":309444.444444445,"type":0},{"id":3,"sLen":0,"time":309583.333333334,"type":0},{"id":0,"sLen":0,"time":309722.222222222,"type":0},{"id":2,"sLen":0,"time":309861.111111111,"type":0},{"id":0,"sLen":0,"time":310000,"type":0},{"id":1,"sLen":0,"time":310138.888888889,"type":0},{"id":3,"sLen":0,"time":310208.333333334,"type":0},{"id":1,"sLen":0,"time":310277.777777778,"type":0},{"id":3,"sLen":0,"time":310347.222222223,"type":0},{"id":1,"sLen":0,"time":310416.666666667,"type":0},{"id":3,"sLen":0,"time":310486.111111111,"type":0},{"id":2,"sLen":416.666666666686,"time":310555.555555556,"type":0}],"characters":["stargazer-3D-dark","stargazer-3D","stargazer-3D-anim","stargazer-red"],"type":0,"visible":false,"strumPos":[0,50],"vocalsSuffix":"-Opponent","strumLinePos":0.25},{"strumScale":0.7,"position":"boyfriend","notes":[{"id":0,"sLen":0,"time":76666.6666666666,"type":0},{"id":1,"sLen":0,"time":76666.6666666667,"type":1},{"id":3,"sLen":0,"time":76944.4444444444,"type":0},{"id":0,"sLen":0,"time":77222.2222222222,"type":0},{"id":1,"sLen":0,"time":77500,"type":0},{"id":1,"sLen":0,"time":77777.7777777777,"type":0},{"id":2,"sLen":0,"time":78055.5555555555,"type":0},{"id":3,"sLen":0,"time":78194.4444444444,"type":0},{"id":0,"sLen":0,"time":78333.3333333333,"type":0},{"id":2,"sLen":0,"time":78611.1111111111,"type":0},{"id":0,"sLen":0,"time":78888.8888888888,"type":0},{"id":3,"sLen":0,"time":79166.6666666666,"type":0},{"id":2,"sLen":416.666666666672,"time":79444.4444444444,"type":0},{"id":0,"sLen":0,"time":80000,"type":0},{"id":1,"sLen":0,"time":80277.7777777777,"type":0},{"id":0,"sLen":0,"time":80555.5555555555,"type":0},{"id":2,"sLen":0,"time":80694.4444444444,"type":0},{"id":1,"sLen":138.888888888891,"time":80833.3333333333,"type":0},{"id":3,"sLen":138.888888888891,"time":81111.1111111111,"type":0},{"id":2,"sLen":138.888888888891,"time":81388.8888888888,"type":0},{"id":3,"sLen":0,"time":81666.6666666666,"type":0},{"id":1,"sLen":0,"time":81805.5555555555,"type":0},{"id":3,"sLen":0,"time":81944.4444444444,"type":0},{"id":2,"sLen":138.888888888891,"time":82083.3333333333,"type":0},{"id":1,"sLen":0,"time":82361.1111111111,"type":0},{"id":3,"sLen":0,"time":82500,"type":0},{"id":2,"sLen":0,"time":82638.8888888888,"type":0},{"id":0,"sLen":0,"time":82777.7777777777,"type":0},{"id":3,"sLen":0,"time":82916.6666666666,"type":0},{"id":1,"sLen":0,"time":83055.5555555555,"type":0},{"id":2,"sLen":0,"time":83194.4444444444,"type":0},{"id":0,"sLen":0,"time":83333.3333333333,"type":0},{"id":1,"sLen":0,"time":83611.1111111111,"type":0},{"id":2,"sLen":0,"time":83750,"type":0},{"id":0,"sLen":0,"time":83888.8888888888,"type":0},{"id":3,"sLen":0,"time":84027.7777777777,"type":0},{"id":1,"sLen":138.888888888891,"time":84166.6666666666,"type":0},{"id":2,"sLen":138.888888888891,"time":84444.4444444444,"type":0},{"id":0,"sLen":0,"time":84722.2222222222,"type":0},{"id":1,"sLen":0,"time":84861.1111111111,"type":0},{"id":0,"sLen":0,"time":85000,"type":0},{"id":2,"sLen":0,"time":85277.7777777777,"type":0},{"id":1,"sLen":0,"time":85416.6666666666,"type":0},{"id":3,"sLen":0,"time":85555.5555555555,"type":0},{"id":0,"sLen":0,"time":85694.4444444444,"type":0},{"id":2,"sLen":0,"time":85833.3333333333,"type":0},{"id":3,"sLen":0,"time":85972.2222222222,"type":0},{"id":2,"sLen":0,"time":86111.1111111111,"type":0},{"id":1,"sLen":0,"time":86249.9999999999,"type":0},{"id":3,"sLen":0,"time":86388.8888888888,"type":0},{"id":0,"sLen":0,"time":86527.7777777777,"type":0},{"id":2,"sLen":0,"time":86666.6666666666,"type":0},{"id":1,"sLen":0,"time":86805.5555555555,"type":0},{"id":0,"sLen":0,"time":86944.4444444444,"type":0},{"id":1,"sLen":0,"time":87083.3333333333,"type":0},{"id":3,"sLen":0,"time":87222.2222222222,"type":0},{"id":1,"sLen":0,"time":87361.1111111111,"type":0},{"id":2,"sLen":0,"time":87499.9999999999,"type":0},{"id":0,"sLen":0,"time":87638.8888888888,"type":0},{"id":1,"sLen":0,"time":87777.7777777777,"type":0},{"id":3,"sLen":0,"time":87916.6666666666,"type":0},{"id":0,"sLen":0,"time":88055.5555555555,"type":0},{"id":2,"sLen":0,"time":88194.4444444444,"type":0},{"id":1,"sLen":0,"time":88333.3333333333,"type":0},{"id":3,"sLen":0,"time":88472.2222222222,"type":0},{"id":2,"sLen":0,"time":88611.1111111111,"type":0},{"id":3,"sLen":0,"time":88749.9999999999,"type":0},{"id":0,"sLen":0,"time":88888.8888888888,"type":0},{"id":3,"sLen":0,"time":89027.7777777777,"type":0},{"id":1,"sLen":0,"time":89166.6666666666,"type":0},{"id":2,"sLen":0,"time":89305.5555555555,"type":0},{"id":0,"sLen":0,"time":89444.4444444444,"type":0},{"id":1,"sLen":0,"time":89583.3333333333,"type":0},{"id":0,"sLen":0,"time":89722.2222222222,"type":0},{"id":3,"sLen":0,"time":89861.1111111111,"type":0},{"id":2,"sLen":1388.88888888889,"time":89999.9999999999,"type":0},{"id":1,"sLen":694.444444444438,"time":91666.6666666666,"type":0},{"id":3,"sLen":694.444444444438,"time":92499.9999999999,"type":0},{"id":0,"sLen":0,"time":93333.3333333333,"type":0},{"id":1,"sLen":0,"time":93472.2222222221,"type":0},{"id":0,"sLen":1111.11111111111,"time":93611.111111111,"type":0},{"id":2,"sLen":694.444444444438,"time":94999.9999999999,"type":0},{"id":3,"sLen":694.444444444438,"time":95833.3333333333,"type":0},{"id":1,"sLen":138.888888888891,"time":96388.8888888888,"type":0},{"id":2,"sLen":1111.11111111111,"time":96666.6666666666,"type":0},{"id":2,"sLen":138.888888888891,"time":101666.666666667,"type":0},{"id":3,"sLen":138.888888888891,"time":102083.333333333,"type":0},{"id":2,"sLen":138.888888888891,"time":102500,"type":0},{"id":1,"sLen":0,"time":102916.666666667,"type":0},{"id":0,"sLen":0,"time":103055.555555555,"type":0},{"id":1,"sLen":0,"time":103194.444444444,"type":0},{"id":2,"sLen":416.666666666672,"time":103333.333333333,"type":0},{"id":3,"sLen":0,"time":103888.888888889,"type":0},{"id":0,"sLen":0,"time":104027.777777778,"type":0},{"id":3,"sLen":416.666666666672,"time":104166.666666667,"type":0},{"id":2,"sLen":0,"time":104722.222222222,"type":0},{"id":1,"sLen":0,"time":104861.111111111,"type":0},{"id":2,"sLen":416.666666666672,"time":105000,"type":0},{"id":3,"sLen":0,"time":105555.555555555,"type":0},{"id":1,"sLen":0,"time":105694.444444444,"type":0},{"id":2,"sLen":416.666666666672,"time":105833.333333333,"type":0},{"id":3,"sLen":0,"time":106388.888888889,"type":0},{"id":2,"sLen":0,"time":106527.777777778,"type":0},{"id":1,"sLen":416.666666666672,"time":106666.666666667,"type":0},{"id":0,"sLen":0,"time":107222.222222222,"type":0},{"id":1,"sLen":0,"time":107361.111111111,"type":0},{"id":0,"sLen":416.666666666657,"time":107500,"type":0},{"id":2,"sLen":0,"time":108055.555555555,"type":0},{"id":3,"sLen":0,"time":108194.444444444,"type":0},{"id":2,"sLen":416.666666666672,"time":108333.333333333,"type":0},{"id":3,"sLen":0,"time":108888.888888889,"type":0},{"id":1,"sLen":0,"time":109027.777777778,"type":0},{"id":2,"sLen":416.666666666672,"time":109166.666666667,"type":0},{"id":3,"sLen":0,"time":109722.222222222,"type":0},{"id":1,"sLen":0,"time":109861.111111111,"type":0},{"id":0,"sLen":138.888888888891,"time":110000,"type":0},{"id":2,"sLen":208.333333333328,"time":110277.777777778,"type":0},{"id":1,"sLen":69.444444444438,"time":110625,"type":0},{"id":3,"sLen":138.888888888891,"time":110833.333333333,"type":0},{"id":2,"sLen":208.333333333328,"time":111111.111111111,"type":0},{"id":0,"sLen":69.444444444438,"time":111458.333333333,"type":0},{"id":1,"sLen":138.888888888891,"time":111666.666666667,"type":0},{"id":2,"sLen":208.333333333328,"time":111944.444444444,"type":0},{"id":0,"sLen":69.444444444438,"time":112291.666666667,"type":0},{"id":3,"sLen":138.888888888891,"time":112500,"type":0},{"id":1,"sLen":138.888888888891,"time":112777.777777778,"type":0},{"id":0,"sLen":138.888888888891,"time":113055.555555555,"type":0},{"id":3,"sLen":138.888888888891,"time":113333.333333333,"type":0},{"id":2,"sLen":208.333333333343,"time":113611.111111111,"type":0},{"id":1,"sLen":69.444444444438,"time":113958.333333333,"type":0},{"id":3,"sLen":138.888888888891,"time":114166.666666667,"type":0},{"id":2,"sLen":208.333333333328,"time":114444.444444444,"type":0},{"id":1,"sLen":69.4444444444525,"time":114791.666666667,"type":0},{"id":3,"sLen":138.88888888892,"time":115000,"type":0},{"id":2,"sLen":208.333333333328,"time":115277.777777778,"type":0},{"id":0,"sLen":69.4444444444525,"time":115625,"type":0},{"id":1,"sLen":416.666666666672,"time":115833.333333333,"type":0},{"id":3,"sLen":0,"time":116388.888888889,"type":0},{"id":0,"sLen":0,"time":116527.777777778,"type":0},{"id":1,"sLen":1805.55555555556,"time":116666.666666667,"type":0},{"id":0,"sLen":0,"time":118888.888888889,"type":1},{"id":0,"sLen":0,"time":120972.222222222,"type":0},{"id":2,"sLen":277.777777777781,"time":121111.111111111,"type":0},{"id":1,"sLen":0,"time":121527.777777778,"type":0},{"id":3,"sLen":0,"time":121666.666666667,"type":0},{"id":0,"sLen":0,"time":121805.555555555,"type":0},{"id":2,"sLen":0,"time":121944.444444444,"type":0},{"id":1,"sLen":555.555555555547,"time":122083.333333333,"type":0},{"id":0,"sLen":0,"time":123194.444444444,"type":0},{"id":2,"sLen":0,"time":123333.333333333,"type":0},{"id":3,"sLen":0,"time":123611.111111111,"type":0},{"id":0,"sLen":0,"time":123750,"type":0},{"id":1,"sLen":0,"time":124027.777777778,"type":0},{"id":1,"sLen":138.888888888876,"time":124305.555555555,"type":0},{"id":3,"sLen":0,"time":124583.333333333,"type":0},{"id":2,"sLen":416.666666666672,"time":124722.222222222,"type":0},{"id":0,"sLen":0,"time":125416.666666667,"type":0},{"id":1,"sLen":138.888888888876,"time":125555.555555555,"type":0},{"id":2,"sLen":0,"time":125833.333333333,"type":0},{"id":0,"sLen":277.777777777781,"time":125972.222222222,"type":0},{"id":2,"sLen":0,"time":126388.888888889,"type":0},{"id":1,"sLen":0,"time":126666.666666667,"type":0},{"id":3,"sLen":138.888888888891,"time":127222.222222222,"type":0},{"id":1,"sLen":0,"time":127500,"type":0},{"id":2,"sLen":833.333333333328,"time":127638.888888889,"type":0},{"id":1,"sLen":0,"time":128611.111111111,"type":0},{"id":0,"sLen":0,"time":128750,"type":0},{"id":2,"sLen":0,"time":128888.888888889,"type":0},{"id":3,"sLen":0,"time":128888.888888889,"type":0},{"id":1,"sLen":0,"time":129027.777777778,"type":0},{"id":2,"sLen":0,"time":129166.666666667,"type":0},{"id":0,"sLen":0,"time":129305.555555555,"type":0},{"id":2,"sLen":0,"time":129444.444444444,"type":0},{"id":3,"sLen":0,"time":129444.444444444,"type":0},{"id":1,"sLen":277.777777777781,"time":129583.333333333,"type":0},{"id":1,"sLen":0,"time":131111.111111111,"type":0},{"id":3,"sLen":0,"time":131111.111111111,"type":0},{"id":2,"sLen":0,"time":131250,"type":0},{"id":1,"sLen":0,"time":131388.888888889,"type":0},{"id":3,"sLen":0,"time":131527.777777778,"type":0},{"id":0,"sLen":0,"time":131666.666666667,"type":0},{"id":1,"sLen":0,"time":131666.666666667,"type":0},{"id":2,"sLen":277.777777777781,"time":131805.555555555,"type":0},{"id":0,"sLen":0,"time":133333.333333333,"type":0},{"id":1,"sLen":0,"time":133333.333333333,"type":0},{"id":2,"sLen":0,"time":133472.222222222,"type":0},{"id":1,"sLen":0,"time":133611.111111111,"type":0},{"id":0,"sLen":0,"time":133750,"type":0},{"id":1,"sLen":0,"time":133888.888888889,"type":0},{"id":2,"sLen":0,"time":133888.888888889,"type":0},{"id":3,"sLen":277.777777777781,"time":134027.777777778,"type":0},{"id":0,"sLen":0,"time":134444.444444444,"type":1},{"id":0,"sLen":0,"time":135555.555555555,"type":0},{"id":1,"sLen":0,"time":135555.555555555,"type":0},{"id":2,"sLen":0,"time":135694.444444444,"type":0},{"id":1,"sLen":0,"time":135833.333333333,"type":0},{"id":3,"sLen":0,"time":135972.222222222,"type":0},{"id":0,"sLen":0,"time":136111.111111111,"type":0},{"id":2,"sLen":138.888888888876,"time":136111.111111111,"type":0},{"id":1,"sLen":0,"time":136388.888888889,"type":0},{"id":3,"sLen":694.444444444438,"time":136527.777777778,"type":0},{"id":0,"sLen":0,"time":137500,"type":0},{"id":2,"sLen":0,"time":163055.555555556,"type":1},{"id":2,"sLen":0,"time":164722.222222222,"type":0},{"id":1,"sLen":0,"time":164861.111111111,"type":0},{"id":3,"sLen":0,"time":165000,"type":0},{"id":1,"sLen":0,"time":165138.888888889,"type":0},{"id":2,"sLen":138.888888888847,"time":165416.666666667,"type":0},{"id":1,"sLen":0,"time":165694.444444444,"type":0},{"id":3,"sLen":0,"time":165833.333333333,"type":0},{"id":0,"sLen":0,"time":165972.222222222,"type":0},{"id":2,"sLen":0,"time":166111.111111111,"type":0},{"id":0,"sLen":0,"time":166250,"type":0},{"id":3,"sLen":0,"time":166388.888888889,"type":0},{"id":2,"sLen":138.888888888876,"time":166527.777777778,"type":0},{"id":1,"sLen":0,"time":166805.555555555,"type":0},{"id":2,"sLen":0,"time":166944.444444444,"type":0},{"id":0,"sLen":0,"time":167083.333333333,"type":0},{"id":1,"sLen":0,"time":167222.222222222,"type":0},{"id":2,"sLen":0,"time":167361.111111111,"type":0},{"id":0,"sLen":0,"time":167500,"type":0},{"id":1,"sLen":0,"time":167638.888888889,"type":0},{"id":3,"sLen":0,"time":167777.777777778,"type":0},{"id":0,"sLen":0,"time":167916.666666667,"type":0},{"id":2,"sLen":0,"time":168055.555555555,"type":0},{"id":3,"sLen":0,"time":168194.444444444,"type":0},{"id":2,"sLen":0,"time":168333.333333333,"type":0},{"id":0,"sLen":0,"time":168472.222222222,"type":0},{"id":3,"sLen":0,"time":168611.111111111,"type":0},{"id":2,"sLen":0,"time":168750,"type":0},{"id":1,"sLen":0,"time":169027.777777778,"type":0},{"id":2,"sLen":0,"time":169305.555555555,"type":0},{"id":1,"sLen":0,"time":169444.444444444,"type":0},{"id":3,"sLen":0,"time":169583.333333333,"type":0},{"id":2,"sLen":0,"time":169722.222222222,"type":0},{"id":0,"sLen":0,"time":169861.111111111,"type":0},{"id":3,"sLen":0,"time":169907.407407407,"type":0},{"id":1,"sLen":138.888888888876,"time":170000,"type":0},{"id":2,"sLen":0,"time":170138.888888889,"type":0},{"id":0,"sLen":138.888888888876,"time":170277.777777778,"type":0},{"id":2,"sLen":0,"time":170416.666666667,"type":0},{"id":1,"sLen":0,"time":170555.555555555,"type":0},{"id":3,"sLen":0,"time":170694.444444444,"type":0},{"id":2,"sLen":0,"time":170833.333333333,"type":0},{"id":1,"sLen":138.888888888876,"time":170972.222222222,"type":0},{"id":2,"sLen":0,"time":171250,"type":0},{"id":1,"sLen":0,"time":171388.888888889,"type":0},{"id":0,"sLen":0,"time":171527.777777778,"type":0},{"id":1,"sLen":0,"time":171736.111111111,"type":0},{"id":2,"sLen":0,"time":171805.555555555,"type":0},{"id":0,"sLen":0,"time":171944.444444444,"type":0},{"id":1,"sLen":0,"time":172083.333333333,"type":0},{"id":0,"sLen":0,"time":172291.666666667,"type":0},{"id":2,"sLen":138.888888888876,"time":172361.111111111,"type":0},{"id":1,"sLen":0,"time":172638.888888889,"type":0},{"id":0,"sLen":0,"time":172777.777777778,"type":0},{"id":3,"sLen":0,"time":172916.666666667,"type":0},{"id":1,"sLen":0,"time":173055.555555555,"type":0},{"id":2,"sLen":0,"time":173194.444444444,"type":0},{"id":3,"sLen":0,"time":173333.333333333,"type":0},{"id":2,"sLen":1666.66666666666,"time":173472.222222222,"type":0},{"id":0,"sLen":972.222222222219,"time":175555.555555555,"type":0},{"id":3,"sLen":416.666666666657,"time":176666.666666667,"type":0},{"id":1,"sLen":416.666666666657,"time":177222.222222222,"type":0},{"id":0,"sLen":0,"time":177777.777777778,"type":1},{"id":2,"sLen":1944.44444444444,"time":177777.777777778,"type":0},{"id":1,"sLen":1944.44444444444,"time":180000,"type":0},{"id":2,"sLen":138.888888888876,"time":182500,"type":0},{"id":0,"sLen":0,"time":182777.777777778,"type":0},{"id":3,"sLen":0,"time":182916.666666667,"type":0},{"id":1,"sLen":0,"time":183055.555555555,"type":0},{"id":0,"sLen":0,"time":183194.444444444,"type":0},{"id":1,"sLen":0,"time":183333.333333333,"type":0},{"id":3,"sLen":0,"time":183472.222222222,"type":0},{"id":1,"sLen":0,"time":183611.111111111,"type":0},{"id":0,"sLen":138.888888888876,"time":183750,"type":0},{"id":2,"sLen":0,"time":184027.777777778,"type":0},{"id":1,"sLen":0,"time":184166.666666667,"type":0},{"id":3,"sLen":0,"time":184305.555555555,"type":0},{"id":1,"sLen":0,"time":184444.444444444,"type":0},{"id":2,"sLen":0,"time":184583.333333333,"type":0},{"id":3,"sLen":0,"time":184722.222222222,"type":0},{"id":2,"sLen":138.888888888876,"time":184861.111111111,"type":0},{"id":0,"sLen":0,"time":185138.888888889,"type":0},{"id":3,"sLen":0,"time":185277.777777778,"type":0},{"id":1,"sLen":0,"time":185416.666666667,"type":0},{"id":3,"sLen":0,"time":185555.555555555,"type":0},{"id":0,"sLen":0,"time":185694.444444444,"type":0},{"id":3,"sLen":0,"time":185833.333333333,"type":0},{"id":2,"sLen":138.888888888876,"time":185972.222222222,"type":0},{"id":0,"sLen":0,"time":186250,"type":0},{"id":1,"sLen":0,"time":186388.888888889,"type":0},{"id":3,"sLen":0,"time":186527.777777778,"type":0},{"id":1,"sLen":0,"time":186666.666666667,"type":0},{"id":0,"sLen":0,"time":186805.555555555,"type":0},{"id":1,"sLen":0,"time":186944.444444444,"type":0},{"id":2,"sLen":138.888888888876,"time":187083.333333333,"type":0},{"id":0,"sLen":0,"time":187361.111111111,"type":0},{"id":3,"sLen":0,"time":187500,"type":0},{"id":2,"sLen":0,"time":187638.888888889,"type":0},{"id":3,"sLen":138.888888888876,"time":187777.777777778,"type":0},{"id":2,"sLen":0,"time":188055.555555555,"type":0},{"id":0,"sLen":0,"time":188194.444444444,"type":0},{"id":1,"sLen":0,"time":188333.333333333,"type":0},{"id":3,"sLen":0,"time":188472.222222222,"type":0},{"id":2,"sLen":0,"time":188611.111111111,"type":0},{"id":0,"sLen":0,"time":188750,"type":0},{"id":3,"sLen":138.888888888876,"time":188888.888888889,"type":0},{"id":0,"sLen":138.888888888876,"time":189305.555555555,"type":0},{"id":1,"sLen":138.888888888876,"time":189722.222222222,"type":0},{"id":2,"sLen":138.888888888876,"time":190000,"type":0},{"id":3,"sLen":138.888888888847,"time":190416.666666667,"type":0},{"id":2,"sLen":138.888888888876,"time":190833.333333333,"type":0},{"id":0,"sLen":555.555555555562,"time":190972.222222222,"type":0},{"id":2,"sLen":416.666666666657,"time":191388.888888889,"type":0},{"id":0,"sLen":138.888888888876,"time":191944.444444444,"type":0},{"id":1,"sLen":416.666666666657,"time":192222.222222222,"type":0},{"id":3,"sLen":0,"time":192222.222222222,"type":1},{"id":2,"sLen":416.666666666657,"time":192777.777777778,"type":0},{"id":0,"sLen":0,"time":193194.444444444,"type":0},{"id":3,"sLen":277.777777777752,"time":193333.333333333,"type":0},{"id":1,"sLen":0,"time":193611.111111111,"type":0},{"id":2,"sLen":277.777777777781,"time":193750,"type":0},{"id":0,"sLen":138.888888888847,"time":194166.666666667,"type":0},{"id":3,"sLen":416.666666666657,"time":194444.444444444,"type":0},{"id":2,"sLen":416.666666666657,"time":195000,"type":0},{"id":1,"sLen":0,"time":195555.555555555,"type":0},{"id":0,"sLen":0,"time":195694.444444444,"type":0},{"id":1,"sLen":0,"time":195833.333333333,"type":0},{"id":3,"sLen":0,"time":195972.222222222,"type":0},{"id":1,"sLen":0,"time":196111.111111111,"type":0},{"id":0,"sLen":0,"time":196250,"type":0},{"id":3,"sLen":0,"time":196388.888888889,"type":0},{"id":2,"sLen":0,"time":196527.777777778,"type":0},{"id":3,"sLen":0,"time":196666.666666667,"type":0},{"id":1,"sLen":0,"time":196805.555555555,"type":0},{"id":2,"sLen":0,"time":196944.444444444,"type":0},{"id":0,"sLen":0,"time":197083.333333333,"type":0},{"id":1,"sLen":0,"time":197222.222222222,"type":0},{"id":3,"sLen":0,"time":197361.111111111,"type":0},{"id":2,"sLen":0,"time":197500,"type":0},{"id":0,"sLen":0,"time":197638.888888889,"type":0},{"id":3,"sLen":0,"time":197777.777777778,"type":0},{"id":1,"sLen":0,"time":197916.666666666,"type":0},{"id":2,"sLen":0,"time":198055.555555555,"type":0},{"id":0,"sLen":0,"time":198194.444444444,"type":0},{"id":3,"sLen":0,"time":198333.333333333,"type":0},{"id":1,"sLen":0,"time":198472.222222222,"type":0},{"id":0,"sLen":0,"time":198611.111111111,"type":0},{"id":2,"sLen":0,"time":198750,"type":0},{"id":1,"sLen":0,"time":198888.888888889,"type":0},{"id":0,"sLen":0,"time":199027.777777778,"type":0},{"id":3,"sLen":0,"time":199166.666666666,"type":0},{"id":1,"sLen":0,"time":199305.555555555,"type":0},{"id":2,"sLen":416.666666666657,"time":199444.444444444,"type":0},{"id":1,"sLen":138.888888888876,"time":200000,"type":0},{"id":3,"sLen":0,"time":200000,"type":0},{"id":0,"sLen":138.888888888876,"time":200277.777777778,"type":0},{"id":3,"sLen":138.888888888876,"time":200555.555555555,"type":0},{"id":0,"sLen":0,"time":200833.333333333,"type":0},{"id":3,"sLen":277.777777777781,"time":200972.222222222,"type":0},{"id":1,"sLen":0,"time":201388.888888889,"type":0},{"id":0,"sLen":0,"time":201527.777777778,"type":0},{"id":2,"sLen":0,"time":201666.666666666,"type":0},{"id":1,"sLen":0,"time":201805.555555555,"type":0},{"id":2,"sLen":0,"time":201944.444444444,"type":0},{"id":0,"sLen":138.888888888876,"time":202083.333333333,"type":0},{"id":1,"sLen":0,"time":202361.111111111,"type":0},{"id":2,"sLen":0,"time":202500,"type":0},{"id":1,"sLen":0,"time":202638.888888889,"type":0},{"id":2,"sLen":0,"time":202777.777777778,"type":0},{"id":0,"sLen":0,"time":202916.666666666,"type":0},{"id":3,"sLen":0,"time":203055.555555555,"type":0},{"id":2,"sLen":138.888888888876,"time":203194.444444444,"type":0},{"id":1,"sLen":0,"time":203472.222222222,"type":0},{"id":0,"sLen":0,"time":203611.111111111,"type":0},{"id":3,"sLen":0,"time":203750,"type":0},{"id":1,"sLen":0,"time":203888.888888889,"type":0},{"id":3,"sLen":0,"time":204027.777777778,"type":0},{"id":2,"sLen":0,"time":204166.666666666,"type":0},{"id":0,"sLen":138.888888888876,"time":204305.555555555,"type":0},{"id":1,"sLen":0,"time":204444.444444444,"type":0},{"id":2,"sLen":0,"time":204583.333333333,"type":0},{"id":0,"sLen":138.888888888876,"time":204722.222222222,"type":0},{"id":1,"sLen":0,"time":204861.111111111,"type":0},{"id":2,"sLen":0,"time":205000,"type":0},{"id":0,"sLen":0,"time":205138.888888889,"type":0},{"id":2,"sLen":0,"time":205277.777777778,"type":0},{"id":3,"sLen":138.888888888876,"time":205416.666666666,"type":0},{"id":2,"sLen":0,"time":205694.444444444,"type":0},{"id":1,"sLen":0,"time":205833.333333333,"type":0},{"id":2,"sLen":0,"time":205972.222222222,"type":0},{"id":0,"sLen":138.888888888847,"time":206111.111111111,"type":0},{"id":3,"sLen":0,"time":206250,"type":0},{"id":2,"sLen":138.888888888876,"time":206388.888888889,"type":0},{"id":1,"sLen":972.222222222219,"time":206666.666666666,"type":0},{"id":3,"sLen":416.666666666657,"time":207777.777777778,"type":0},{"id":0,"sLen":138.888888888876,"time":208333.333333333,"type":0},{"id":3,"sLen":138.888888888905,"time":208611.111111111,"type":0},{"id":1,"sLen":0,"time":208888.888888889,"type":0},{"id":2,"sLen":972.222222222219,"time":208888.888888889,"type":0},{"id":3,"sLen":416.666666666657,"time":210000,"type":0},{"id":0,"sLen":416.666666666686,"time":210555.555555555,"type":0},{"id":2,"sLen":416.666666666657,"time":211111.111111111,"type":0},{"id":1,"sLen":277.777777777781,"time":211527.777777778,"type":0},{"id":0,"sLen":0,"time":211944.444444444,"type":0},{"id":3,"sLen":277.777777777781,"time":212222.222222222,"type":0},{"id":0,"sLen":138.888888888876,"time":212638.888888889,"type":0},{"id":2,"sLen":694.444444444438,"time":213055.555555555,"type":0},{"id":0,"sLen":1527.77777777778,"time":213611.111111111,"type":0},{"id":1,"sLen":972.222222222219,"time":215555.555555555,"type":0},{"id":3,"sLen":416.666666666657,"time":216666.666666666,"type":0},{"id":0,"sLen":416.666666666657,"time":217222.222222222,"type":0},{"id":2,"sLen":138.888888888876,"time":217777.777777778,"type":0},{"id":1,"sLen":0,"time":222500,"type":1},{"id":3,"sLen":138.888888888876,"time":222500,"type":0},{"id":1,"sLen":0,"time":222777.777777778,"type":0},{"id":2,"sLen":416.666666666657,"time":223055.555555555,"type":0},{"id":3,"sLen":138.888888888847,"time":223611.111111111,"type":0},{"id":1,"sLen":0,"time":223888.888888889,"type":0},{"id":2,"sLen":416.666666666657,"time":224166.666666666,"type":0},{"id":3,"sLen":138.888888888876,"time":224722.222222222,"type":0},{"id":2,"sLen":0,"time":225000,"type":0},{"id":1,"sLen":138.888888888876,"time":225277.777777778,"type":0},{"id":2,"sLen":138.888888888876,"time":225555.555555555,"type":0},{"id":1,"sLen":0,"time":225833.333333333,"type":0},{"id":0,"sLen":0,"time":225972.222222222,"type":0},{"id":1,"sLen":0,"time":226111.111111111,"type":0},{"id":3,"sLen":0,"time":226250,"type":0},{"id":0,"sLen":0,"time":226388.888888889,"type":0},{"id":1,"sLen":0,"time":226527.777777778,"type":0},{"id":2,"sLen":0,"time":226805.555555555,"type":0},{"id":1,"sLen":0,"time":226944.444444444,"type":0},{"id":0,"sLen":0,"time":227361.111111111,"type":0},{"id":2,"sLen":0,"time":227500,"type":0},{"id":1,"sLen":0,"time":227638.888888889,"type":0},{"id":2,"sLen":0,"time":227916.666666666,"type":0},{"id":1,"sLen":0,"time":228055.555555555,"type":0},{"id":3,"sLen":0,"time":228333.333333333,"type":0},{"id":2,"sLen":0,"time":228472.222222222,"type":0},{"id":0,"sLen":0,"time":228611.111111111,"type":0},{"id":1,"sLen":0,"time":228750,"type":0},{"id":2,"sLen":0,"time":229027.777777778,"type":0},{"id":1,"sLen":0,"time":229166.666666666,"type":0},{"id":3,"sLen":0,"time":229722.222222222,"type":0},{"id":1,"sLen":0,"time":229861.111111111,"type":0},{"id":2,"sLen":416.666666666686,"time":230000,"type":0},{"id":0,"sLen":416.666666666599,"time":230555.555555555,"type":0},{"id":3,"sLen":138.888888888847,"time":230833.333333333,"type":0},{"id":2,"sLen":972.222222222219,"time":231111.111111111,"type":0},{"id":0,"sLen":416.666666666657,"time":232777.777777778,"type":0},{"id":3,"sLen":972.222222222248,"time":233333.333333333,"type":0},{"id":2,"sLen":0,"time":235000,"type":0},{"id":1,"sLen":0,"time":235277.777777778,"type":0},{"id":0,"sLen":277.777777777752,"time":235555.555555555,"type":0},{"id":2,"sLen":0,"time":235972.222222222,"type":0},{"id":1,"sLen":277.777777777781,"time":236388.888888889,"type":0},{"id":2,"sLen":0,"time":236805.555555555,"type":0},{"id":0,"sLen":0,"time":237083.333333333,"type":0},{"id":3,"sLen":0,"time":237222.222222222,"type":0},{"id":2,"sLen":0,"time":237500,"type":0},{"id":1,"sLen":0,"time":237638.888888889,"type":0},{"id":3,"sLen":972.222222222219,"time":237777.777777778,"type":0},{"id":1,"sLen":416.666666666686,"time":238888.888888889,"type":0},{"id":2,"sLen":416.666666666657,"time":239444.444444444,"type":0},{"id":1,"sLen":416.666666666686,"time":240000,"type":0},{"id":0,"sLen":0,"time":240555.555555555,"type":0},{"id":3,"sLen":0,"time":240833.333333333,"type":0},{"id":0,"sLen":0,"time":240972.222222222,"type":0},{"id":2,"sLen":0,"time":241250,"type":0},{"id":1,"sLen":0,"time":241527.777777778,"type":0},{"id":1,"sLen":0,"time":241805.555555555,"type":0},{"id":2,"sLen":0,"time":241944.444444444,"type":0},{"id":3,"sLen":0,"time":242083.333333333,"type":0},{"id":0,"sLen":0,"time":242222.222222222,"type":0},{"id":2,"sLen":0,"time":242361.111111111,"type":0},{"id":1,"sLen":0,"time":242500,"type":0},{"id":3,"sLen":0,"time":242638.888888889,"type":0},{"id":2,"sLen":138.888888888876,"time":242777.777777778,"type":0},{"id":0,"sLen":0,"time":243055.555555555,"type":0},{"id":2,"sLen":0,"time":243194.444444444,"type":0},{"id":0,"sLen":0,"time":243333.333333333,"type":0},{"id":1,"sLen":0,"time":243472.222222222,"type":0},{"id":2,"sLen":0,"time":243611.111111111,"type":0},{"id":0,"sLen":0,"time":243750,"type":0},{"id":3,"sLen":0,"time":244027.777777778,"type":0},{"id":2,"sLen":0,"time":244166.666666666,"type":0},{"id":1,"sLen":0,"time":244305.555555555,"type":0},{"id":2,"sLen":0,"time":244444.444444444,"type":0},{"id":3,"sLen":0,"time":244722.222222222,"type":0},{"id":1,"sLen":0,"time":244861.111111111,"type":0},{"id":2,"sLen":0,"time":245138.888888889,"type":0},{"id":0,"sLen":0,"time":245277.777777778,"type":0},{"id":1,"sLen":0,"time":245416.666666666,"type":0},{"id":3,"sLen":0,"time":245555.555555555,"type":0},{"id":0,"sLen":0,"time":245694.444444444,"type":0},{"id":2,"sLen":138.888888888905,"time":245833.333333333,"type":0},{"id":1,"sLen":0,"time":246111.111111111,"type":0},{"id":3,"sLen":0,"time":246250,"type":0},{"id":0,"sLen":0,"time":246388.888888889,"type":0},{"id":3,"sLen":0,"time":246527.777777778,"type":0},{"id":2,"sLen":0,"time":246666.666666666,"type":0},{"id":1,"sLen":0,"time":246805.555555555,"type":0},{"id":2,"sLen":0,"time":246944.444444444,"type":0},{"id":0,"sLen":0,"time":247222.222222222,"type":0},{"id":2,"sLen":416.666666666657,"time":247500,"type":0},{"id":3,"sLen":138.888888888818,"time":248055.555555555,"type":0},{"id":1,"sLen":416.666666666686,"time":248333.333333333,"type":0},{"id":2,"sLen":0,"time":248888.888888889,"type":0},{"id":0,"sLen":138.888888888876,"time":249166.666666666,"type":0},{"id":1,"sLen":0,"time":249444.444444444,"type":0},{"id":2,"sLen":138.888888888905,"time":249722.222222222,"type":0},{"id":0,"sLen":0,"time":250000,"type":0},{"id":2,"sLen":0,"time":250208.333333333,"type":0},{"id":1,"sLen":138.888888888876,"time":250277.777777778,"type":0},{"id":3,"sLen":0,"time":250555.555555555,"type":0},{"id":2,"sLen":416.666666666686,"time":250833.333333333,"type":0},{"id":0,"sLen":0,"time":251388.888888889,"type":0},{"id":1,"sLen":0,"time":251666.666666666,"type":0},{"id":2,"sLen":416.666666666686,"time":251944.444444444,"type":0},{"id":0,"sLen":0,"time":252500,"type":0},{"id":3,"sLen":0,"time":252638.888888889,"type":0},{"id":2,"sLen":0,"time":252916.666666666,"type":0},{"id":0,"sLen":0,"time":253055.555555555,"type":0},{"id":1,"sLen":277.777777777781,"time":253194.444444444,"type":0},{"id":3,"sLen":0,"time":253611.111111111,"type":0},{"id":0,"sLen":0,"time":253750,"type":0},{"id":2,"sLen":138.888888888818,"time":253888.888888889,"type":0},{"id":0,"sLen":0,"time":254166.666666666,"type":0},{"id":1,"sLen":277.777777777752,"time":254305.555555555,"type":0},{"id":2,"sLen":0,"time":254722.222222222,"type":0},{"id":3,"sLen":0,"time":254861.111111111,"type":0},{"id":0,"sLen":138.888888888847,"time":255000,"type":0},{"id":2,"sLen":0,"time":255277.777777778,"type":0},{"id":3,"sLen":277.777777777781,"time":255416.666666666,"type":0},{"id":1,"sLen":277.77777777781,"time":255833.333333333,"type":0},{"id":2,"sLen":277.777777777781,"time":256250,"type":0},{"id":0,"sLen":416.666666666657,"time":256666.666666666,"type":0},{"id":2,"sLen":416.666666666686,"time":257222.222222222,"type":0},{"id":0,"sLen":138.888888888876,"time":262222.222222222,"type":0},{"id":3,"sLen":138.888888888876,"time":262500,"type":0},{"id":2,"sLen":138.888888888876,"time":262777.777777778,"type":0},{"id":1,"sLen":0,"time":263055.555555555,"type":0},{"id":2,"sLen":0,"time":263194.444444444,"type":0},{"id":0,"sLen":0,"time":263472.222222222,"type":0},{"id":3,"sLen":0,"time":263750,"type":0},{"id":0,"sLen":0,"time":264027.777777778,"type":0},{"id":1,"sLen":0,"time":264166.666666666,"type":0},{"id":3,"sLen":0,"time":264305.555555555,"type":0},{"id":2,"sLen":0,"time":264444.444444444,"type":0},{"id":3,"sLen":0,"time":264583.333333333,"type":0},{"id":1,"sLen":0,"time":264722.222222222,"type":0},{"id":3,"sLen":0,"time":264861.111111111,"type":0},{"id":0,"sLen":138.888888888876,"time":265000,"type":0},{"id":2,"sLen":0,"time":265277.777777778,"type":0},{"id":1,"sLen":0,"time":265416.666666666,"type":0},{"id":2,"sLen":0,"time":265555.555555555,"type":0},{"id":1,"sLen":0,"time":265694.444444444,"type":0},{"id":0,"sLen":0,"time":265833.333333333,"type":0},{"id":2,"sLen":0,"time":265972.222222222,"type":0},{"id":0,"sLen":0,"time":266111.111111111,"type":0},{"id":1,"sLen":0,"time":266250,"type":0},{"id":3,"sLen":0,"time":266388.888888889,"type":0},{"id":0,"sLen":0,"time":266527.777777778,"type":0},{"id":2,"sLen":833.333333333314,"time":266666.666666666,"type":0},{"id":1,"sLen":0,"time":267638.888888889,"type":0},{"id":3,"sLen":0,"time":267777.777777778,"type":0},{"id":1,"sLen":0,"time":267916.666666666,"type":0},{"id":2,"sLen":0,"time":268055.555555555,"type":0},{"id":0,"sLen":0,"time":268194.444444444,"type":0},{"id":1,"sLen":0,"time":268333.333333333,"type":0},{"id":2,"sLen":0,"time":268472.222222222,"type":0},{"id":0,"sLen":0,"time":268611.111111111,"type":0},{"id":3,"sLen":0,"time":268750,"type":0},{"id":1,"sLen":0,"time":269305.555555555,"type":0},{"id":3,"sLen":0,"time":269583.333333333,"type":0},{"id":1,"sLen":0,"time":269722.222222222,"type":0},{"id":2,"sLen":0,"time":269861.111111111,"type":0},{"id":1,"sLen":0,"time":270000,"type":0},{"id":0,"sLen":0,"time":270138.888888889,"type":0},{"id":3,"sLen":0,"time":270277.777777778,"type":0},{"id":1,"sLen":0,"time":270416.666666666,"type":0},{"id":0,"sLen":0,"time":270555.555555555,"type":0},{"id":2,"sLen":0,"time":270694.444444444,"type":0},{"id":1,"sLen":0,"time":270833.333333333,"type":0},{"id":3,"sLen":0,"time":270972.222222222,"type":0},{"id":1,"sLen":138.888888888876,"time":271111.111111111,"type":0},{"id":2,"sLen":0,"time":271388.888888889,"type":0},{"id":1,"sLen":138.888888888876,"time":271527.777777778,"type":0},{"id":0,"sLen":0,"time":271805.555555555,"type":0},{"id":1,"sLen":0,"time":271944.444444444,"type":0},{"id":3,"sLen":0,"time":272083.333333333,"type":0},{"id":0,"sLen":0,"time":272222.222222222,"type":0},{"id":1,"sLen":138.888888888876,"time":272638.888888889,"type":0},{"id":2,"sLen":0,"time":272916.666666667,"type":0},{"id":0,"sLen":0,"time":273055.555555555,"type":0},{"id":3,"sLen":0,"time":273194.444444444,"type":0},{"id":2,"sLen":138.888888888876,"time":273333.333333333,"type":0},{"id":1,"sLen":0,"time":273611.111111111,"type":0},{"id":2,"sLen":0,"time":273750,"type":0},{"id":1,"sLen":0,"time":274027.777777778,"type":0},{"id":3,"sLen":0,"time":274027.777777778,"type":0},{"id":0,"sLen":0,"time":274166.666666667,"type":0},{"id":2,"sLen":0,"time":274166.666666667,"type":0},{"id":0,"sLen":0,"time":274305.555555555,"type":0},{"id":1,"sLen":0,"time":274305.555555555,"type":0},{"id":1,"sLen":0,"time":274444.444444444,"type":0},{"id":2,"sLen":0,"time":274444.444444444,"type":0},{"id":0,"sLen":0,"time":274861.111111111,"type":0},{"id":3,"sLen":0,"time":274861.111111111,"type":0},{"id":2,"sLen":0,"time":275000,"type":0},{"id":1,"sLen":0,"time":275138.888888889,"type":0},{"id":3,"sLen":0,"time":275277.777777778,"type":0},{"id":0,"sLen":0,"time":275416.666666667,"type":0},{"id":1,"sLen":0,"time":275833.333333333,"type":0},{"id":2,"sLen":138.888888888876,"time":275833.333333333,"type":0},{"id":0,"sLen":138.888888888876,"time":276388.888888889,"type":0},{"id":3,"sLen":0,"time":276388.888888889,"type":0},{"id":1,"sLen":0,"time":276944.444444444,"type":0},{"id":2,"sLen":138.888888888876,"time":276944.444444444,"type":0},{"id":0,"sLen":0,"time":277222.222222222,"type":0},{"id":3,"sLen":0,"time":277222.222222222,"type":0},{"id":1,"sLen":0,"time":277361.111111111,"type":0},{"id":2,"sLen":138.888888888876,"time":277361.111111111,"type":0},{"id":0,"sLen":0,"time":277638.888888889,"type":0},{"id":3,"sLen":0,"time":277638.888888889,"type":0},{"id":1,"sLen":138.888888888876,"time":278055.555555555,"type":0},{"id":3,"sLen":0,"time":278055.555555555,"type":0},{"id":0,"sLen":0,"time":278611.111111111,"type":0},{"id":2,"sLen":138.888888888876,"time":278611.111111111,"type":0},{"id":3,"sLen":0,"time":279166.666666667,"type":0},{"id":0,"sLen":0,"time":279305.555555555,"type":0},{"id":3,"sLen":0,"time":279444.444444444,"type":0},{"id":1,"sLen":138.888888888876,"time":279722.222222222,"type":0},{"id":2,"sLen":0,"time":279722.222222222,"type":0},{"id":1,"sLen":0,"time":280277.777777778,"type":0},{"id":3,"sLen":138.888888888876,"time":280277.777777778,"type":0},{"id":0,"sLen":138.888888888876,"time":280833.333333333,"type":0},{"id":2,"sLen":0,"time":280833.333333333,"type":0},{"id":1,"sLen":0,"time":281388.888888889,"type":0},{"id":3,"sLen":138.888888888876,"time":281388.888888889,"type":0},{"id":0,"sLen":0,"time":281666.666666667,"type":0},{"id":2,"sLen":0,"time":281666.666666667,"type":0},{"id":1,"sLen":0,"time":281805.555555556,"type":0},{"id":3,"sLen":138.888888888876,"time":281805.555555556,"type":0},{"id":0,"sLen":0,"time":282083.333333333,"type":0},{"id":2,"sLen":0,"time":282083.333333333,"type":0},{"id":1,"sLen":0,"time":282500,"type":0},{"id":2,"sLen":138.888888888876,"time":282500,"type":0},{"id":0,"sLen":416.666666666686,"time":283055.555555555,"type":0},{"id":3,"sLen":0,"time":283055.555555555,"type":0},{"id":1,"sLen":0,"time":283611.111111111,"type":0},{"id":2,"sLen":138.888888888876,"time":283611.111111111,"type":0},{"id":3,"sLen":138.888888888876,"time":283888.888888889,"type":0},{"id":0,"sLen":138.888888888876,"time":284166.666666667,"type":0},{"id":3,"sLen":0,"time":284444.444444444,"type":0},{"id":1,"sLen":0,"time":284513.888888889,"type":0},{"id":2,"sLen":138.888888888934,"time":284513.888888889,"type":0},{"id":0,"sLen":0,"time":284722.222222222,"type":0},{"id":3,"sLen":0,"time":285000,"type":0},{"id":0,"sLen":0,"time":285138.888888889,"type":0},{"id":1,"sLen":0,"time":285277.777777778,"type":0},{"id":2,"sLen":138.888888888876,"time":285277.777777778,"type":0},{"id":0,"sLen":0,"time":285555.555555555,"type":0},{"id":3,"sLen":138.888888888876,"time":285555.555555555,"type":0},{"id":1,"sLen":0,"time":285833.333333333,"type":0},{"id":2,"sLen":0,"time":285833.333333333,"type":0},{"id":3,"sLen":0,"time":285972.222222222,"type":0},{"id":0,"sLen":138.888888889458,"time":286111.111111111,"type":0},{"id":1,"sLen":0,"time":286111.111111111,"type":0},{"id":1,"sLen":138.888888888934,"time":286388.888888889,"type":0},{"id":3,"sLen":0,"time":286388.888888889,"type":0},{"id":0,"sLen":0,"time":286666.666666667,"type":0},{"id":1,"sLen":0,"time":286736.111111111,"type":0},{"id":2,"sLen":138.888888889458,"time":286736.111111111,"type":0},{"id":3,"sLen":0,"time":286944.444444444,"type":0},{"id":1,"sLen":0,"time":287222.222222222,"type":0},{"id":2,"sLen":0,"time":287222.222222222,"type":0},{"id":0,"sLen":0,"time":287361.111111111,"type":0},{"id":1,"sLen":0,"time":287500,"type":0},{"id":2,"sLen":0,"time":287777.777777778,"type":0},{"id":3,"sLen":0,"time":287777.777777778,"type":0},{"id":0,"sLen":138.888888888876,"time":288055.555555556,"type":0},{"id":1,"sLen":0,"time":288333.333333333,"type":0},{"id":2,"sLen":138.888888888876,"time":288333.333333333,"type":0},{"id":3,"sLen":0,"time":288611.111111111,"type":0},{"id":1,"sLen":0,"time":288888.888888889,"type":0},{"id":0,"sLen":0,"time":288958.333333333,"type":0},{"id":2,"sLen":138.888888888876,"time":288958.333333333,"type":0},{"id":1,"sLen":0,"time":289166.666666667,"type":0},{"id":3,"sLen":0,"time":289444.444444444,"type":0},{"id":0,"sLen":0,"time":289583.333333333,"type":0},{"id":1,"sLen":0,"time":289722.222222222,"type":0},{"id":2,"sLen":138.888888888876,"time":289722.222222222,"type":0},{"id":0,"sLen":0,"time":290000,"type":0},{"id":3,"sLen":0,"time":290000,"type":0},{"id":1,"sLen":0,"time":290277.777777778,"type":0},{"id":2,"sLen":0,"time":290277.777777778,"type":0},{"id":3,"sLen":0,"time":290416.666666667,"type":0},{"id":0,"sLen":138.888888888876,"time":290555.555555556,"type":0},{"id":2,"sLen":0,"time":290555.555555556,"type":0},{"id":1,"sLen":0,"time":290833.333333333,"type":0},{"id":2,"sLen":138.888888888876,"time":290833.333333333,"type":0},{"id":0,"sLen":0,"time":291111.111111111,"type":0},{"id":1,"sLen":277.777777777752,"time":291180.555555556,"type":0},{"id":3,"sLen":416.666666666686,"time":291388.888888889,"type":0},{"id":0,"sLen":138.888888888876,"time":291666.666666667,"type":0},{"id":2,"sLen":138.888888888876,"time":292777.777777778,"type":0},{"id":3,"sLen":138.888888888876,"time":293055.555555556,"type":0},{"id":0,"sLen":0,"time":293611.111111111,"type":0},{"id":2,"sLen":138.888888889458,"time":293611.111111111,"type":0},{"id":0,"sLen":138.888888888876,"time":294166.666666667,"type":0},{"id":2,"sLen":0,"time":294166.666666667,"type":0},{"id":1,"sLen":0,"time":294722.222222222,"type":0},{"id":3,"sLen":138.888888888876,"time":294722.222222222,"type":0},{"id":0,"sLen":0,"time":295000,"type":0},{"id":1,"sLen":138.888888888876,"time":295138.888888889,"type":0},{"id":3,"sLen":0,"time":295138.888888889,"type":0},{"id":0,"sLen":0,"time":295416.666666667,"type":0},{"id":1,"sLen":0,"time":295833.333333333,"type":0},{"id":2,"sLen":138.888888888876,"time":295833.333333333,"type":0},{"id":0,"sLen":138.888888888876,"time":296388.888888889,"type":0},{"id":3,"sLen":0,"time":296388.888888889,"type":0},{"id":1,"sLen":0,"time":296944.444444445,"type":0},{"id":3,"sLen":0,"time":297083.333333333,"type":0},{"id":1,"sLen":0,"time":297222.222222222,"type":0},{"id":0,"sLen":0,"time":297500,"type":0},{"id":2,"sLen":138.888888888876,"time":297500,"type":0},{"id":1,"sLen":0,"time":297777.777777778,"type":0},{"id":3,"sLen":0,"time":297777.777777778,"type":0},{"id":0,"sLen":0,"time":297916.666666667,"type":0},{"id":2,"sLen":0,"time":298055.555555556,"type":0},{"id":0,"sLen":0,"time":298194.444444445,"type":0},{"id":1,"sLen":0,"time":298333.333333333,"type":0},{"id":3,"sLen":0,"time":298333.333333333,"type":0},{"id":2,"sLen":0,"time":298472.222222222,"type":0},{"id":0,"sLen":0,"time":298611.111111111,"type":0},{"id":1,"sLen":0,"time":298750,"type":0},{"id":2,"sLen":0,"time":298888.888888889,"type":0},{"id":3,"sLen":0,"time":298888.888888889,"type":0},{"id":1,"sLen":0,"time":299027.777777778,"type":0},{"id":0,"sLen":0,"time":299166.666666667,"type":0},{"id":3,"sLen":0,"time":299305.555555556,"type":0},{"id":1,"sLen":0,"time":299444.444444445,"type":0},{"id":2,"sLen":0,"time":299444.444444445,"type":0},{"id":0,"sLen":0,"time":299583.333333333,"type":0},{"id":1,"sLen":0,"time":299722.222222222,"type":0},{"id":0,"sLen":0,"time":299861.111111111,"type":0},{"id":2,"sLen":0,"time":300000,"type":0},{"id":3,"sLen":0,"time":300000,"type":0},{"id":0,"sLen":0,"time":300138.888888889,"type":0},{"id":1,"sLen":0,"time":300277.777777778,"type":0},{"id":3,"sLen":0,"time":300416.666666667,"type":0},{"id":0,"sLen":0,"time":300555.555555556,"type":0},{"id":2,"sLen":0,"time":300555.555555556,"type":0},{"id":3,"sLen":0,"time":300694.444444445,"type":0},{"id":1,"sLen":0,"time":300833.333333333,"type":0},{"id":0,"sLen":0,"time":300972.222222222,"type":0},{"id":2,"sLen":0,"time":301111.111111111,"type":0},{"id":3,"sLen":0,"time":301111.111111111,"type":0},{"id":1,"sLen":0,"time":301250,"type":0},{"id":0,"sLen":0,"time":301388.888888889,"type":0},{"id":1,"sLen":0,"time":301527.777777778,"type":0},{"id":2,"sLen":0,"time":301666.666666667,"type":0},{"id":3,"sLen":0,"time":301666.666666667,"type":0},{"id":0,"sLen":0,"time":301805.555555556,"type":0},{"id":1,"sLen":0,"time":301944.444444445,"type":0},{"id":3,"sLen":0,"time":302083.333333333,"type":0},{"id":0,"sLen":0,"time":302500,"type":0},{"id":2,"sLen":0,"time":302500,"type":0},{"id":3,"sLen":0,"time":302777.777777778,"type":0},{"id":1,"sLen":0,"time":302916.666666667,"type":0},{"id":0,"sLen":0,"time":303055.555555556,"type":0},{"id":2,"sLen":0,"time":303055.555555556,"type":0},{"id":1,"sLen":138.888888888876,"time":303333.333333334,"type":0},{"id":2,"sLen":0,"time":303611.111111111,"type":0},{"id":0,"sLen":0,"time":303750,"type":0},{"id":2,"sLen":0,"time":303888.888888889,"type":0},{"id":3,"sLen":138.888888888876,"time":303888.888888889,"type":0},{"id":0,"sLen":138.888888888876,"time":304166.666666667,"type":0},{"id":1,"sLen":0,"time":304444.444444445,"type":0},{"id":2,"sLen":138.888888888876,"time":304513.888888889,"type":0},{"id":3,"sLen":0,"time":304513.888888889,"type":0},{"id":1,"sLen":0,"time":304722.222222222,"type":0},{"id":0,"sLen":0,"time":305000,"type":0},{"id":2,"sLen":0,"time":305000,"type":0},{"id":3,"sLen":0,"time":305138.888888889,"type":0},{"id":2,"sLen":0,"time":305277.777777778,"type":0},{"id":1,"sLen":138.888888888876,"time":305555.555555556,"type":0},{"id":3,"sLen":0,"time":305555.555555556,"type":0},{"id":0,"sLen":0,"time":305833.333333334,"type":0},{"id":3,"sLen":0,"time":305972.222222222,"type":0},{"id":1,"sLen":0,"time":306111.111111111,"type":0},{"id":2,"sLen":138.888888889458,"time":306111.111111111,"type":0},{"id":3,"sLen":0,"time":306388.888888889,"type":0},{"id":1,"sLen":0,"time":306666.666666667,"type":0},{"id":2,"sLen":138.888888888876,"time":306666.666666667,"type":0},{"id":0,"sLen":138.888888888876,"time":306944.444444445,"type":0},{"id":3,"sLen":138.888888888876,"time":307222.222222222,"type":0},{"id":2,"sLen":0,"time":307500,"type":0},{"id":1,"sLen":416.666666666686,"time":307777.777777778,"type":0},{"id":2,"sLen":416.666666666686,"time":308333.333333334,"type":0},{"id":0,"sLen":416.666666666686,"time":308888.888888889,"type":0},{"id":3,"sLen":416.666666666744,"time":309444.444444445,"type":0},{"id":0,"sLen":0,"time":310000,"type":0},{"id":1,"sLen":0,"time":310138.888888889,"type":0},{"id":3,"sLen":0,"time":310208.333333334,"type":0},{"id":1,"sLen":0,"time":310277.777777778,"type":0},{"id":3,"sLen":0,"time":310347.222222223,"type":0},{"id":1,"sLen":0,"time":310416.666666667,"type":0},{"id":3,"sLen":0,"time":310486.111111111,"type":0},{"id":2,"sLen":416.666666666686,"time":310555.555555556,"type":0}],"characters":["sonic","sonic-anim","sonic-super"],"type":1,"visible":true,"strumPos":[0,50],"vocalsSuffix":"-Player","strumLinePos":0.67}],"codenameChart":true,"stage":"dream","noteTypes":["Gem Note"]}