{
	"animations": [
		{
			"offsets": [
				-157,
				-346
			],
			"loop": false,
			"fps": 24,
			"anim": "singLEFT",
			"indices": [],
			"name": "GOREFIELD L"
		},
		{
			"offsets": [
				-159,
				-382
			],
			"loop": false,
			"fps": 24,
			"anim": "singDOWN",
			"indices": [],
			"name": "GOREFIELD D"
		},
		{
			"offsets": [
				-159,
				-345
			],
			"loop": false,
			"fps": 24,
			"anim": "singUP",
			"indices": [],
			"name": "GOREFIELD U"
		},
		{
			"offsets": [
				-159,
				-350
			],
			"loop": false,
			"fps": 24,
			"anim": "singRIGHT",
			"indices": [],
			"name": "GOREFIELD R"
		},
		{
			"offsets": [
				-160,
				-350
			],
			"loop": false,
			"fps": 24,
			"anim": "idle",
			"indices": [],
			"name": "GOREFIELD I"
		},
		{
			"offsets": [
				-147,
				-262
			],
			"indices": [],
			"fps": 24,
			"anim": "transformation",
			"loop": false,
			"name": "GOREFIELD TF"
		}
	],
	"vocals_file": "",
	"no_antialiasing": false,
	"image": "characters/altergarfield",
	"position": [
		240,
		165
	],
	"healthicon": "altergarfield",
	"flip_x": false,
	"healthbar_colors": [
		212,
		117,
		60
	],
	"camera_position": [
		200,
		400
	],
	"sing_duration": 6.1,
	"scale": 1,
	"_editor_isPlayer": false
}