<?xml version='1.0' encoding='utf-8'?>
<TextureAtlas imagePath="abnormal_getup.png"><SubTexture name="abnormal_getup anim0000" x="1268" y="4384" width="1246" height="1129" frameX="-1195" frameY="-1017" frameWidth="3299" frameHeight="2505" />
<SubTexture name="abnormal_getup anim0001" x="0" y="4384" width="1268" height="1132" frameX="-1195" frameY="-864" frameWidth="3299" frameHeight="2505" />
<SubTexture name="abnormal_getup anim0002" x="5574" y="0" width="1241" height="1276" frameX="-1195" frameY="-685" frameWidth="3299" frameHeight="2505" />
<SubTexture name="abnormal_getup anim0003" x="5574" y="0" width="1241" height="1276" frameX="-1195" frameY="-685" frameWidth="3299" frameHeight="2505" />
<SubTexture name="abnormal_getup anim0004" x="4459" y="1458" width="1114" height="1441" frameX="-1187" frameY="-520" frameWidth="3299" frameHeight="2505" />
<SubTexture name="abnormal_getup anim0005" x="4459" y="1458" width="1114" height="1441" frameX="-1187" frameY="-520" frameWidth="3299" frameHeight="2505" />
<SubTexture name="abnormal_getup anim0006" x="4459" y="2899" width="1114" height="1441" frameX="-1187" frameY="-520" frameWidth="3299" frameHeight="2505" />
<SubTexture name="abnormal_getup anim0007" x="3345" y="2925" width="1114" height="1441" frameX="-1187" frameY="-520" frameWidth="3299" frameHeight="2505" />
<SubTexture name="abnormal_getup anim0008" x="0" y="2925" width="1115" height="1459" frameX="-1154" frameY="-502" frameWidth="3299" frameHeight="2505" />
<SubTexture name="abnormal_getup anim0009" x="1115" y="2925" width="1115" height="1459" frameX="-1154" frameY="-502" frameWidth="3299" frameHeight="2505" />
<SubTexture name="abnormal_getup anim0010" x="2230" y="0" width="1115" height="1462" frameX="-1146" frameY="-499" frameWidth="3299" frameHeight="2505" />
<SubTexture name="abnormal_getup anim0011" x="0" y="1463" width="1115" height="1462" frameX="-1146" frameY="-499" frameWidth="3299" frameHeight="2505" />
<SubTexture name="abnormal_getup anim0012" x="1115" y="1463" width="1115" height="1462" frameX="-1146" frameY="-499" frameWidth="3299" frameHeight="2505" />
<SubTexture name="abnormal_getup anim0013" x="2230" y="1463" width="1115" height="1462" frameX="-1146" frameY="-499" frameWidth="3299" frameHeight="2505" />
<SubTexture name="abnormal_getup anim0014" x="2230" y="2925" width="1115" height="1458" frameX="-1135" frameY="-503" frameWidth="3299" frameHeight="2505" />
<SubTexture name="abnormal_getup anim0015" x="4459" y="0" width="1115" height="1458" frameX="-1135" frameY="-503" frameWidth="3299" frameHeight="2505" />
<SubTexture name="abnormal_getup anim0016" x="3345" y="0" width="1114" height="1461" frameX="-1140" frameY="-500" frameWidth="3299" frameHeight="2505" />
<SubTexture name="abnormal_getup anim0017" x="3345" y="1461" width="1114" height="1461" frameX="-1140" frameY="-500" frameWidth="3299" frameHeight="2505" />
<SubTexture name="abnormal_getup anim0018" x="0" y="0" width="1115" height="1463" frameX="-1143" frameY="-498" frameWidth="3299" frameHeight="2505" />
<SubTexture name="abnormal_getup anim0019" x="1115" y="0" width="1115" height="1463" frameX="-1143" frameY="-498" frameWidth="3299" frameHeight="2505" />
</TextureAtlas>
