{
	"animations": [
		{
			"offsets": [
				-40,
				0
			],
			"loop": false,
			"fps": 20,
			"anim": "singLEFT",
			"indices": [],
			"name": "bh singLEFT"
		},
		{
			"offsets": [
				0,
				20
			],
			"loop": false,
			"fps": 20,
			"anim": "singDOWN",
			"indices": [],
			"name": "bh singDOWN"
		},
		{
			"offsets": [
				-16,
				9
			],
			"loop": false,
			"fps": 20,
			"anim": "singUP",
			"indices": [],
			"name": "bh singUP"
		},
		{
			"offsets": [
				-12,
				4
			],
			"loop": false,
			"fps": 20,
			"anim": "singRIGHT",
			"indices": [],
			"name": "bh singRIGHT"
		},
		{
			"loop": true,
			"offsets": [
				0,
				0
			],
			"anim": "idle",
			"fps": 20,
			"name": "static idle",
			"indices": []
		}
	],
	"no_antialiasing": false,
	"image": "characters/static",
	"position": [
		-80,
		-232
	],
	"healthicon": "dad",
	"flip_x": false,
	"healthbar_colors": [
		0,
		0,
		0
	],
	"camera_position": [
		-590,
		-340
	],
	"sing_duration": 340.1,
	"scale": 2.8
}