<!DOCTYPE codename-mod-options>

<menu name="Song Options" desc="Specific settings for the songs in the mod.">
    <menu name="Genesis Options" desc="Toggles for events, shaders, and mechanics in Genesis.">
		<checkbox id="null" name="NMI gyat" desc=":tongue:"/>
    </menu>
    <menu name="Forever Dream Options" desc="Toggles for events, shaders, and mechanics in Forever Dream.">
        <checkbox id="fdNTSC" name="NTSC Shader" desc="If enabled, applies a NTSC shader over the whole game."/>

        <checkbox id="fdBloom" name="Bloom Shader" desc="If enabled, applies a Bloom shader over Stage and snow."/>
        <checkbox id="fdGlitch" name="Glitch Shader" desc="If enabled, applies a Glitch shader in certain events and snow too lol."/>
        <checkbox id="fdIvert" name="Invert Shader" desc="If enabled, applies Ivert shader in certain events."/>
    <choice id="fdResolution" name="Resolution" desc="Changes the window resolution.">
    <value name="836 x 720" value="small"/>
		<value name="1120 x 960" value="big"/>
	  </choice>
		<checkbox id="fdGameCamPixel" name="Game Pixel Shader" desc="If enabled, applies a pixel perfect shader over the characters and background."/>
		<checkbox id="fdHUDCamPixel" name="UI Pixel Shader" desc="If enabled, applies a pixelated shader over all UI elements."/>
		<checkbox id="fdFlicker" name="Flicker Backgrounds" desc="If enabled, causes the background to flicker as part of song events."/>
		<checkbox id="fdMechanics" name="Mechanics" desc="Disable this if you don't want to experience song mechanics."/>
    </menu>
    <menu name="Premeditated Options" desc="Toggles for events, shaders, and mechanics in Premeditated.">
		<checkbox id="premedPcFuckery" name="Pc Mechanics" desc="Disable this if you dont want Premeditated to mess with your pc! (Removing the taskbar, changing your wallpaper, etc.)"/>
    </menu>
    <menu name="Classic Options" desc="Toggles for events, shaders, and mechanics in Classic.">
		<checkbox id="null" name="insert option here" desc=""/>
    </menu>

	<checkbox id="moyDrainHealth" name="Health Drain" desc="If enabled, the opponent drains your health whenever they hit a note. Health can be gained back."/>
</menu>