<?xml version='1.0' encoding='utf-8'?>
<TextureAtlas imagePath="bf_anger.png"><SubTexture name="bf_anger idle dance0000" x="633" y="3007" width="635" height="676" frameX="-777" frameY="-960" frameWidth="2160" frameHeight="2302" />
<SubTexture name="bf_anger idle dance0001" x="633" y="3007" width="635" height="676" frameX="-777" frameY="-960" frameWidth="2160" frameHeight="2302" />
<SubTexture name="bf_anger idle dance0002" x="3149" y="0" width="629" height="684" frameX="-780" frameY="-952" frameWidth="2160" frameHeight="2302" />
<SubTexture name="bf_anger idle dance0003" x="3149" y="0" width="629" height="684" frameX="-780" frameY="-952" frameWidth="2160" frameHeight="2302" />
<SubTexture name="bf_anger idle dance0004" x="2485" y="1406" width="624" height="691" frameX="-782" frameY="-945" frameWidth="2160" frameHeight="2302" />
<SubTexture name="bf_anger idle dance0005" x="2485" y="1406" width="624" height="691" frameX="-782" frameY="-945" frameWidth="2160" frameHeight="2302" />
<SubTexture name="bf_anger idle dance0006" x="1293" y="1606" width="624" height="705" frameX="-782" frameY="-931" frameWidth="2160" frameHeight="2302" />
<SubTexture name="bf_anger idle dance0007" x="1293" y="1606" width="624" height="705" frameX="-782" frameY="-931" frameWidth="2160" frameHeight="2302" />
<SubTexture name="bf_anger idle dance0008" x="1791" y="714" width="624" height="708" frameX="-782" frameY="-928" frameWidth="2160" frameHeight="2302" />
<SubTexture name="bf_anger idle dance0009" x="1791" y="714" width="624" height="708" frameX="-782" frameY="-928" frameWidth="2160" frameHeight="2302" />
<SubTexture name="bf_anger down note0000" x="1217" y="3684" width="619" height="563" frameX="-781" frameY="-1069" frameWidth="2160" frameHeight="2302" />
<SubTexture name="bf_anger down note0001" x="1217" y="3684" width="619" height="563" frameX="-781" frameY="-1069" frameWidth="2160" frameHeight="2302" />
<SubTexture name="bf_anger down note0002" x="607" y="3684" width="610" height="583" frameX="-788" frameY="-1049" frameWidth="2160" frameHeight="2302" />
<SubTexture name="bf_anger down note0003" x="607" y="3684" width="610" height="583" frameX="-788" frameY="-1049" frameWidth="2160" frameHeight="2302" />
<SubTexture name="bf_anger down note0004" x="0" y="3684" width="607" height="589" frameX="-791" frameY="-1043" frameWidth="2160" frameHeight="2302" />
<SubTexture name="bf_anger left note0000" x="1791" y="0" width="694" height="714" frameX="-734" frameY="-922" frameWidth="2160" frameHeight="2302" />
<SubTexture name="bf_anger left note0001" x="1791" y="0" width="694" height="714" frameX="-734" frameY="-922" frameWidth="2160" frameHeight="2302" />
<SubTexture name="bf_anger left note0002" x="0" y="1606" width="669" height="708" frameX="-750" frameY="-928" frameWidth="2160" frameHeight="2302" />
<SubTexture name="bf_anger left note0003" x="0" y="1606" width="669" height="708" frameX="-750" frameY="-928" frameWidth="2160" frameHeight="2302" />
<SubTexture name="bf_anger left note0004" x="2485" y="0" width="664" height="704" frameX="-754" frameY="-932" frameWidth="2160" frameHeight="2302" />
<SubTexture name="bf_anger right note0000" x="0" y="2314" width="713" height="693" frameX="-808" frameY="-943" frameWidth="2160" frameHeight="2302" />
<SubTexture name="bf_anger right note0001" x="0" y="2314" width="713" height="693" frameX="-808" frameY="-943" frameWidth="2160" frameHeight="2302" />
<SubTexture name="bf_anger right note0002" x="713" y="2314" width="681" height="692" frameX="-805" frameY="-944" frameWidth="2160" frameHeight="2302" />
<SubTexture name="bf_anger right note0003" x="713" y="2314" width="681" height="692" frameX="-805" frameY="-944" frameWidth="2160" frameHeight="2302" />
<SubTexture name="bf_anger right note0004" x="1394" y="2314" width="667" height="692" frameX="-802" frameY="-944" frameWidth="2160" frameHeight="2302" />
<SubTexture name="bf_anger up note0000" x="0" y="0" width="573" height="833" frameX="-840" frameY="-800" frameWidth="2160" frameHeight="2302" />
<SubTexture name="bf_anger up note0001" x="0" y="0" width="573" height="833" frameX="-840" frameY="-800" frameWidth="2160" frameHeight="2302" />
<SubTexture name="bf_anger up note0002" x="1208" y="0" width="583" height="785" frameX="-835" frameY="-848" frameWidth="2160" frameHeight="2302" />
<SubTexture name="bf_anger up note0003" x="1208" y="0" width="583" height="785" frameX="-835" frameY="-848" frameWidth="2160" frameHeight="2302" />
<SubTexture name="bf_anger up note0004" x="0" y="833" width="582" height="773" frameX="-835" frameY="-860" frameWidth="2160" frameHeight="2302" />
<SubTexture name="bf_anger brace0000" x="2456" y="3007" width="576" height="659" frameX="-840" frameY="-977" frameWidth="2160" frameHeight="2302" />
<SubTexture name="bf_anger reaction0000" x="2456" y="3007" width="576" height="659" frameX="-840" frameY="-977" frameWidth="2160" frameHeight="2302" />
<SubTexture name="bf_anger reaction0001" x="3032" y="3007" width="576" height="659" frameX="-840" frameY="-977" frameWidth="2160" frameHeight="2302" />
<SubTexture name="bf_anger reaction0002" x="3032" y="3007" width="576" height="659" frameX="-840" frameY="-977" frameWidth="2160" frameHeight="2302" />
<SubTexture name="bf_anger reaction0003" x="3778" y="0" width="576" height="659" frameX="-840" frameY="-977" frameWidth="2160" frameHeight="2302" />
<SubTexture name="bf_anger reaction0004" x="3778" y="0" width="576" height="659" frameX="-840" frameY="-977" frameWidth="2160" frameHeight="2302" />
<SubTexture name="bf_anger reaction0005" x="1874" y="3007" width="582" height="663" frameX="-840" frameY="-973" frameWidth="2160" frameHeight="2302" />
<SubTexture name="bf_anger reaction0006" x="1874" y="3007" width="582" height="663" frameX="-840" frameY="-973" frameWidth="2160" frameHeight="2302" />
<SubTexture name="bf_anger reaction0007" x="1268" y="3007" width="606" height="667" frameX="-829" frameY="-969" frameWidth="2160" frameHeight="2302" />
<SubTexture name="bf_anger reaction0008" x="1268" y="3007" width="606" height="667" frameX="-829" frameY="-969" frameWidth="2160" frameHeight="2302" />
<SubTexture name="bf_anger reaction0009" x="3149" y="2032" width="602" height="670" frameX="-840" frameY="-966" frameWidth="2160" frameHeight="2302" />
<SubTexture name="bf_anger reaction0010" x="3149" y="2032" width="602" height="670" frameX="-840" frameY="-966" frameWidth="2160" frameHeight="2302" />
<SubTexture name="bf_anger reaction0011" x="3149" y="1359" width="606" height="673" frameX="-840" frameY="-963" frameWidth="2160" frameHeight="2302" />
<SubTexture name="bf_anger reaction0012" x="3149" y="1359" width="606" height="673" frameX="-840" frameY="-963" frameWidth="2160" frameHeight="2302" />
<SubTexture name="bf_anger reaction0013" x="3149" y="684" width="606" height="675" frameX="-840" frameY="-961" frameWidth="2160" frameHeight="2302" />
<SubTexture name="bf_anger reaction0014" x="3149" y="684" width="606" height="675" frameX="-840" frameY="-961" frameWidth="2160" frameHeight="2302" />
<SubTexture name="bf_anger reaction0015" x="3149" y="684" width="606" height="675" frameX="-840" frameY="-961" frameWidth="2160" frameHeight="2302" />
<SubTexture name="bf_anger reaction0016" x="3149" y="684" width="606" height="675" frameX="-840" frameY="-961" frameWidth="2160" frameHeight="2302" />
<SubTexture name="bf_anger reaction0017" x="3149" y="684" width="606" height="675" frameX="-840" frameY="-961" frameWidth="2160" frameHeight="2302" />
<SubTexture name="bf_anger reaction0018" x="3149" y="684" width="606" height="675" frameX="-840" frameY="-961" frameWidth="2160" frameHeight="2302" />
<SubTexture name="bf_anger reaction0019" x="3149" y="684" width="606" height="675" frameX="-840" frameY="-961" frameWidth="2160" frameHeight="2302" />
<SubTexture name="bf_anger reaction0020" x="3149" y="684" width="606" height="675" frameX="-840" frameY="-961" frameWidth="2160" frameHeight="2302" />
<SubTexture name="bf_anger reaction0021" x="3149" y="684" width="606" height="675" frameX="-840" frameY="-961" frameWidth="2160" frameHeight="2302" />
<SubTexture name="bf_anger reaction0022" x="3149" y="684" width="606" height="675" frameX="-840" frameY="-961" frameWidth="2160" frameHeight="2302" />
<SubTexture name="bf_anger reaction0023" x="582" y="833" width="639" height="718" frameX="-775" frameY="-918" frameWidth="2160" frameHeight="2302" />
<SubTexture name="bf_anger reaction0024" x="582" y="833" width="639" height="718" frameX="-775" frameY="-918" frameWidth="2160" frameHeight="2302" />
<SubTexture name="bf_anger reaction0025" x="0" y="3007" width="633" height="677" frameX="-778" frameY="-959" frameWidth="2160" frameHeight="2302" />
<SubTexture name="bf_anger reaction0026" x="0" y="3007" width="633" height="677" frameX="-778" frameY="-959" frameWidth="2160" frameHeight="2302" />
<SubTexture name="bf_anger reaction0027" x="2061" y="2314" width="624" height="686" frameX="-782" frameY="-950" frameWidth="2160" frameHeight="2302" />
<SubTexture name="bf_anger reaction0028" x="2061" y="2314" width="624" height="686" frameX="-782" frameY="-950" frameWidth="2160" frameHeight="2302" />
<SubTexture name="bf_anger reaction0029" x="2485" y="704" width="624" height="702" frameX="-782" frameY="-934" frameWidth="2160" frameHeight="2302" />
<SubTexture name="bf_anger reaction0030" x="2485" y="704" width="624" height="702" frameX="-782" frameY="-934" frameWidth="2160" frameHeight="2302" />
<SubTexture name="bf_anger reaction0031" x="669" y="1606" width="624" height="706" frameX="-782" frameY="-930" frameWidth="2160" frameHeight="2302" />
<SubTexture name="bf_anger reaction0032" x="669" y="1606" width="624" height="706" frameX="-782" frameY="-930" frameWidth="2160" frameHeight="2302" />
<SubTexture name="bf_anger miss0000" x="573" y="0" width="635" height="803" frameX="-814" frameY="-832" frameWidth="2160" frameHeight="2302" />
<SubTexture name="bf_anger miss0001" x="573" y="0" width="635" height="803" frameX="-814" frameY="-832" frameWidth="2160" frameHeight="2302" />
<SubTexture name="bf_anger miss0002" x="573" y="0" width="635" height="803" frameX="-814" frameY="-832" frameWidth="2160" frameHeight="2302" />
</TextureAtlas>
