<?xml version='1.0' encoding='utf-8'?>
<TextureAtlas imagePath="BF_confirmation.png"><SubTexture name="BF_confirmation idle dance0000" x="3208" y="4153" width="668" height="684" frameX="-744" frameY="-952" frameWidth="2160" frameHeight="2302" />
<SubTexture name="BF_confirmation idle dance0001" x="3208" y="4153" width="668" height="684" frameX="-744" frameY="-952" frameWidth="2160" frameHeight="2302" />
<SubTexture name="BF_confirmation idle dance0002" x="2547" y="4153" width="661" height="686" frameX="-749" frameY="-950" frameWidth="2160" frameHeight="2302" />
<SubTexture name="BF_confirmation idle dance0003" x="2547" y="4153" width="661" height="686" frameX="-749" frameY="-950" frameWidth="2160" frameHeight="2302" />
<SubTexture name="BF_confirmation idle dance0004" x="1280" y="4153" width="658" height="688" frameX="-756" frameY="-948" frameWidth="2160" frameHeight="2302" />
<SubTexture name="BF_confirmation idle dance0005" x="1280" y="4153" width="658" height="688" frameX="-756" frameY="-948" frameWidth="2160" frameHeight="2302" />
<SubTexture name="BF_confirmation idle dance0006" x="3417" y="3410" width="666" height="701" frameX="-752" frameY="-935" frameWidth="2160" frameHeight="2302" />
<SubTexture name="BF_confirmation idle dance0007" x="3417" y="3410" width="666" height="701" frameX="-752" frameY="-935" frameWidth="2160" frameHeight="2302" />
<SubTexture name="BF_confirmation idle dance0008" x="1390" y="3410" width="665" height="704" frameX="-754" frameY="-932" frameWidth="2160" frameHeight="2302" />
<SubTexture name="BF_confirmation idle dance0009" x="1390" y="3410" width="665" height="704" frameX="-754" frameY="-932" frameWidth="2160" frameHeight="2302" />
<SubTexture name="BF_confirmation left note0000" x="2055" y="3410" width="699" height="703" frameX="-695" frameY="-933" frameWidth="2160" frameHeight="2302" />
<SubTexture name="BF_confirmation left note0001" x="2055" y="3410" width="699" height="703" frameX="-695" frameY="-933" frameWidth="2160" frameHeight="2302" />
<SubTexture name="BF_confirmation left note0002" x="4521" y="0" width="697" height="697" frameX="-699" frameY="-939" frameWidth="2160" frameHeight="2302" />
<SubTexture name="BF_confirmation left note0003" x="4521" y="0" width="697" height="697" frameX="-699" frameY="-939" frameWidth="2160" frameHeight="2302" />
<SubTexture name="BF_confirmation left note0004" x="4521" y="2788" width="696" height="695" frameX="-701" frameY="-941" frameWidth="2160" frameHeight="2302" />
<SubTexture name="BF_confirmation idle ALT0000" x="3117" y="1623" width="671" height="803" frameX="-743" frameY="-833" frameWidth="2160" frameHeight="2302" />
<SubTexture name="BF_confirmation idle ALT0001" x="3117" y="1623" width="671" height="803" frameX="-743" frameY="-833" frameWidth="2160" frameHeight="2302" />
<SubTexture name="BF_confirmation idle ALT0002" x="720" y="2607" width="673" height="802" frameX="-740" frameY="-834" frameWidth="2160" frameHeight="2302" />
<SubTexture name="BF_confirmation idle ALT0003" x="720" y="2607" width="673" height="802" frameX="-740" frameY="-834" frameWidth="2160" frameHeight="2302" />
<SubTexture name="BF_confirmation idle ALT0004" x="3117" y="816" width="670" height="807" frameX="-744" frameY="-829" frameWidth="2160" frameHeight="2302" />
<SubTexture name="BF_confirmation idle ALT0005" x="3117" y="816" width="670" height="807" frameX="-744" frameY="-829" frameWidth="2160" frameHeight="2302" />
<SubTexture name="BF_confirmation idle ALT0006" x="2484" y="0" width="633" height="842" frameX="-784" frameY="-794" frameWidth="2160" frameHeight="2302" />
<SubTexture name="BF_confirmation idle ALT0007" x="2484" y="0" width="633" height="842" frameX="-784" frameY="-794" frameWidth="2160" frameHeight="2302" />
<SubTexture name="BF_confirmation idle ALT0008" x="1853" y="0" width="631" height="844" frameX="-788" frameY="-792" frameWidth="2160" frameHeight="2302" />
<SubTexture name="BF_confirmation idle ALT0009" x="1853" y="0" width="631" height="844" frameX="-788" frameY="-792" frameWidth="2160" frameHeight="2302" />
<SubTexture name="BF_confirmation right note0000" x="0" y="4153" width="658" height="695" frameX="-821" frameY="-941" frameWidth="2160" frameHeight="2302" />
<SubTexture name="BF_confirmation right note0001" x="0" y="4153" width="658" height="695" frameX="-821" frameY="-941" frameWidth="2160" frameHeight="2302" />
<SubTexture name="BF_confirmation right note0002" x="4521" y="697" width="640" height="697" frameX="-820" frameY="-939" frameWidth="2160" frameHeight="2302" />
<SubTexture name="BF_confirmation right note0003" x="4521" y="697" width="640" height="697" frameX="-820" frameY="-939" frameWidth="2160" frameHeight="2302" />
<SubTexture name="BF_confirmation right note0004" x="4521" y="1394" width="634" height="697" frameX="-819" frameY="-939" frameWidth="2160" frameHeight="2302" />
<SubTexture name="BF_confirmation down note0000" x="5218" y="0" width="688" height="579" frameX="-714" frameY="-1053" frameWidth="2160" frameHeight="2302" />
<SubTexture name="BF_confirmation down note0001" x="5218" y="0" width="688" height="579" frameX="-714" frameY="-1053" frameWidth="2160" frameHeight="2302" />
<SubTexture name="BF_confirmation down note0002" x="3876" y="4153" width="686" height="589" frameX="-712" frameY="-1043" frameWidth="2160" frameHeight="2302" />
<SubTexture name="BF_confirmation down note0003" x="3876" y="4153" width="686" height="589" frameX="-712" frameY="-1043" frameWidth="2160" frameHeight="2302" />
<SubTexture name="BF_confirmation down note0004" x="4521" y="3483" width="690" height="594" frameX="-708" frameY="-1038" frameWidth="2160" frameHeight="2302" />
<SubTexture name="BF_confirmation up note0000" x="1393" y="2607" width="701" height="766" frameX="-735" frameY="-869" frameWidth="2160" frameHeight="2302" />
<SubTexture name="BF_confirmation up note0001" x="1393" y="2607" width="701" height="766" frameX="-735" frameY="-869" frameWidth="2160" frameHeight="2302" />
<SubTexture name="BF_confirmation up note0002" x="2094" y="2607" width="709" height="751" frameX="-732" frameY="-884" frameWidth="2160" frameHeight="2302" />
<SubTexture name="BF_confirmation up note0003" x="2094" y="2607" width="709" height="751" frameX="-732" frameY="-884" frameWidth="2160" frameHeight="2302" />
<SubTexture name="BF_confirmation up note0004" x="0" y="3410" width="707" height="743" frameX="-734" frameY="-892" frameWidth="2160" frameHeight="2302" />
<SubTexture name="BF_confirmation ALT down0000" x="2803" y="2607" width="673" height="747" frameX="-728" frameY="-885" frameWidth="2160" frameHeight="2302" />
<SubTexture name="BF_confirmation ALT down0001" x="2803" y="2607" width="673" height="747" frameX="-728" frameY="-885" frameWidth="2160" frameHeight="2302" />
<SubTexture name="BF_confirmation ALT down0002" x="3846" y="0" width="675" height="745" frameX="-723" frameY="-887" frameWidth="2160" frameHeight="2302" />
<SubTexture name="BF_confirmation ALT down0003" x="3846" y="0" width="675" height="745" frameX="-723" frameY="-887" frameWidth="2160" frameHeight="2302" />
<SubTexture name="BF_confirmation ALT down0004" x="707" y="3410" width="683" height="736" frameX="-715" frameY="-896" frameWidth="2160" frameHeight="2302" />
<SubTexture name="BF_confirmation ALT left0000" x="1980" y="1770" width="697" height="818" frameX="-697" frameY="-818" frameWidth="2160" frameHeight="2302" />
<SubTexture name="BF_confirmation ALT left0001" x="1980" y="1770" width="697" height="818" frameX="-697" frameY="-818" frameWidth="2160" frameHeight="2302" />
<SubTexture name="BF_confirmation ALT left0002" x="1309" y="1770" width="671" height="828" frameX="-725" frameY="-808" frameWidth="2160" frameHeight="2302" />
<SubTexture name="BF_confirmation ALT left0003" x="1309" y="1770" width="671" height="828" frameX="-725" frameY="-808" frameWidth="2160" frameHeight="2302" />
<SubTexture name="BF_confirmation ALT left0004" x="658" y="1770" width="651" height="833" frameX="-745" frameY="-803" frameWidth="2160" frameHeight="2302" />
<SubTexture name="BF_confirmation ALT right0000" x="0" y="1770" width="658" height="837" frameX="-821" frameY="-799" frameWidth="2160" frameHeight="2302" />
<SubTexture name="BF_confirmation ALT right0001" x="0" y="1770" width="658" height="837" frameX="-821" frameY="-799" frameWidth="2160" frameHeight="2302" />
<SubTexture name="BF_confirmation ALT right0002" x="635" y="921" width="640" height="845" frameX="-820" frameY="-791" frameWidth="2160" frameHeight="2302" />
<SubTexture name="BF_confirmation ALT right0003" x="635" y="921" width="640" height="845" frameX="-820" frameY="-791" frameWidth="2160" frameHeight="2302" />
<SubTexture name="BF_confirmation ALT right0004" x="0" y="921" width="635" height="849" frameX="-819" frameY="-787" frameWidth="2160" frameHeight="2302" />
<SubTexture name="BF_confirmation ALT up0000" x="0" y="0" width="606" height="921" frameX="-830" frameY="-714" frameWidth="2160" frameHeight="2302" />
<SubTexture name="BF_confirmation ALT up0001" x="0" y="0" width="606" height="921" frameX="-830" frameY="-714" frameWidth="2160" frameHeight="2302" />
<SubTexture name="BF_confirmation ALT up0002" x="606" y="0" width="619" height="895" frameX="-822" frameY="-740" frameWidth="2160" frameHeight="2302" />
<SubTexture name="BF_confirmation ALT up0003" x="606" y="0" width="619" height="895" frameX="-822" frameY="-740" frameWidth="2160" frameHeight="2302" />
<SubTexture name="BF_confirmation ALT up0004" x="1225" y="0" width="628" height="886" frameX="-813" frameY="-749" frameWidth="2160" frameHeight="2302" />
<SubTexture name="BF_confirmation miss0000" x="0" y="2607" width="720" height="803" frameX="-729" frameY="-832" frameWidth="2160" frameHeight="2302" />
<SubTexture name="BF_confirmation miss0001" x="0" y="2607" width="720" height="803" frameX="-729" frameY="-832" frameWidth="2160" frameHeight="2302" />
<SubTexture name="BF_confirmation miss0002" x="0" y="2607" width="720" height="803" frameX="-729" frameY="-832" frameWidth="2160" frameHeight="2302" />
<SubTexture name="BF_confirmation miss0003" x="0" y="2607" width="720" height="803" frameX="-729" frameY="-832" frameWidth="2160" frameHeight="2302" />
<SubTexture name="BF_confirmation miss0004" x="0" y="2607" width="720" height="803" frameX="-729" frameY="-832" frameWidth="2160" frameHeight="2302" />
<SubTexture name="BF_confirmation alt miss0000" x="3117" y="0" width="729" height="816" frameX="-720" frameY="-819" frameWidth="2160" frameHeight="2302" />
<SubTexture name="BF_confirmation alt miss0001" x="3117" y="0" width="729" height="816" frameX="-720" frameY="-819" frameWidth="2160" frameHeight="2302" />
<SubTexture name="BF_confirmation alt miss0002" x="3117" y="0" width="729" height="816" frameX="-720" frameY="-819" frameWidth="2160" frameHeight="2302" />
<SubTexture name="BF_confirmation alt miss0003" x="3117" y="0" width="729" height="816" frameX="-720" frameY="-819" frameWidth="2160" frameHeight="2302" />
<SubTexture name="BF_confirmation alt miss0004" x="3117" y="0" width="729" height="816" frameX="-720" frameY="-819" frameWidth="2160" frameHeight="2302" />
<SubTexture name="BF_confirmation ewthisanimationissobad0000" x="2484" y="842" width="594" height="701" frameX="-764" frameY="-948" frameWidth="2160" frameHeight="2302" />
<SubTexture name="BF_confirmation ewthisanimationissobad0001" x="2484" y="842" width="594" height="701" frameX="-764" frameY="-948" frameWidth="2160" frameHeight="2302" />
<SubTexture name="BF_confirmation ewthisanimationissobad0002" x="1853" y="844" width="599" height="699" frameX="-759" frameY="-950" frameWidth="2160" frameHeight="2302" />
<SubTexture name="BF_confirmation ewthisanimationissobad0003" x="1853" y="844" width="599" height="699" frameX="-759" frameY="-950" frameWidth="2160" frameHeight="2302" />
<SubTexture name="BF_confirmation ewthisanimationissobad0004" x="3846" y="1453" width="601" height="706" frameX="-757" frameY="-943" frameWidth="2160" frameHeight="2302" />
<SubTexture name="BF_confirmation ewthisanimationissobad0005" x="3846" y="1453" width="601" height="706" frameX="-757" frameY="-943" frameWidth="2160" frameHeight="2302" />
<SubTexture name="BF_confirmation ewthisanimationissobad0006" x="3846" y="745" width="607" height="708" frameX="-751" frameY="-941" frameWidth="2160" frameHeight="2302" />
<SubTexture name="BF_confirmation ewthisanimationissobad0007" x="3846" y="745" width="607" height="708" frameX="-751" frameY="-941" frameWidth="2160" frameHeight="2302" />
<SubTexture name="BF_confirmation ewthisanimationissobad0008" x="3846" y="745" width="607" height="708" frameX="-751" frameY="-941" frameWidth="2160" frameHeight="2302" />
<SubTexture name="BF_confirmation ewthisanimationissobad0009" x="3846" y="745" width="607" height="708" frameX="-751" frameY="-941" frameWidth="2160" frameHeight="2302" />
<SubTexture name="BF_confirmation ewthisanimationissobad0010" x="3846" y="2159" width="570" height="706" frameX="-757" frameY="-943" frameWidth="2160" frameHeight="2302" />
<SubTexture name="BF_confirmation ewthisanimationissobad0011" x="3846" y="2159" width="570" height="706" frameX="-757" frameY="-943" frameWidth="2160" frameHeight="2302" />
<SubTexture name="BF_confirmation ewthisanimationissobad0012" x="1938" y="4153" width="609" height="687" frameX="-790" frameY="-948" frameWidth="2160" frameHeight="2302" />
<SubTexture name="BF_confirmation ewthisanimationissobad0013" x="1938" y="4153" width="609" height="687" frameX="-790" frameY="-948" frameWidth="2160" frameHeight="2302" />
<SubTexture name="BF_confirmation ewthisanimationissobad0014" x="658" y="4153" width="622" height="691" frameX="-785" frameY="-944" frameWidth="2160" frameHeight="2302" />
<SubTexture name="BF_confirmation ewthisanimationissobad0015" x="658" y="4153" width="622" height="691" frameX="-785" frameY="-944" frameWidth="2160" frameHeight="2302" />
<SubTexture name="BF_confirmation ewthisanimationissobad0016" x="4521" y="2091" width="645" height="697" frameX="-773" frameY="-939" frameWidth="2160" frameHeight="2302" />
<SubTexture name="BF_confirmation ewthisanimationissobad0017" x="2754" y="3410" width="663" height="702" frameX="-757" frameY="-934" frameWidth="2160" frameHeight="2302" />
</TextureAtlas>
