<?xml version='1.0' encoding='utf-8'?>
<TextureAtlas imagePath="na_scythe.png"><SubTexture name="na_scythe idle dance0000" x="2199" y="2634" width="1084" height="946" frameX="-1158" frameY="-719" frameWidth="3299" frameHeight="2505" />
<SubTexture name="na_scythe right note0000" x="0" y="5657" width="2039" height="778" frameX="-934" frameY="-708" frameWidth="3299" frameHeight="2505" />
<SubTexture name="na_scythe right note0001" x="2039" y="5657" width="2041" height="776" frameX="-933" frameY="-708" frameWidth="3299" frameHeight="2505" />
<SubTexture name="na_scythe right note0002" x="5661" y="0" width="1982" height="799" frameX="-942" frameY="-715" frameWidth="3299" frameHeight="2505" />
<SubTexture name="na_scythe right note0003" x="5661" y="0" width="1982" height="799" frameX="-942" frameY="-715" frameWidth="3299" frameHeight="2505" />
<SubTexture name="na_scythe right note0004" x="2671" y="4815" width="1961" height="806" frameX="-943" frameY="-719" frameWidth="3299" frameHeight="2505" />
<SubTexture name="na_scythe left note0000" x="3866" y="3946" width="1361" height="845" frameX="-1089" frameY="-705" frameWidth="3299" frameHeight="2505" />
<SubTexture name="na_scythe left note0001" x="0" y="4815" width="1369" height="842" frameX="-1090" frameY="-711" frameWidth="3299" frameHeight="2505" />
<SubTexture name="na_scythe left note0002" x="1369" y="4815" width="1302" height="838" frameX="-1077" frameY="-678" frameWidth="3299" frameHeight="2505" />
<SubTexture name="na_scythe left note0003" x="1369" y="4815" width="1302" height="838" frameX="-1077" frameY="-678" frameWidth="3299" frameHeight="2505" />
<SubTexture name="na_scythe left note0004" x="4387" y="879" width="1266" height="842" frameX="-1087" frameY="-670" frameWidth="3299" frameHeight="2505" />
<SubTexture name="na_scythe up note0000" x="704" y="2634" width="771" height="1293" frameX="-1252" frameY="-111" frameWidth="3299" frameHeight="2505" />
<SubTexture name="na_scythe up note0001" x="1475" y="2634" width="724" height="1288" frameX="-1296" frameY="-115" frameWidth="3299" frameHeight="2505" />
<SubTexture name="na_scythe up note0002" x="0" y="2634" width="704" height="1312" frameX="-1351" frameY="-106" frameWidth="3299" frameHeight="2505" />
<SubTexture name="na_scythe up note0003" x="0" y="2634" width="704" height="1312" frameX="-1351" frameY="-106" frameWidth="3299" frameHeight="2505" />
<SubTexture name="na_scythe up note0004" x="0" y="1319" width="705" height="1315" frameX="-1356" frameY="-107" frameWidth="3299" frameHeight="2505" />
<SubTexture name="na_scythe down note0000" x="4387" y="0" width="1274" height="879" frameX="-1173" frameY="-734" frameWidth="3299" frameHeight="2505" />
<SubTexture name="na_scythe down note0001" x="2580" y="3946" width="1286" height="860" frameX="-1166" frameY="-735" frameWidth="3299" frameHeight="2505" />
<SubTexture name="na_scythe down note0002" x="1291" y="3946" width="1289" height="868" frameX="-1166" frameY="-725" frameWidth="3299" frameHeight="2505" />
<SubTexture name="na_scythe down note0003" x="1291" y="3946" width="1289" height="868" frameX="-1166" frameY="-725" frameWidth="3299" frameHeight="2505" />
<SubTexture name="na_scythe down note0004" x="0" y="3946" width="1291" height="869" frameX="-1165" frameY="-721" frameWidth="3299" frameHeight="2505" />
<SubTexture name="na_scythe oo0000" x="705" y="1319" width="701" height="1313" frameX="-1358" frameY="-107" frameWidth="3299" frameHeight="2505" />
<SubTexture name="na_scythe oo0001" x="705" y="1319" width="701" height="1313" frameX="-1358" frameY="-107" frameWidth="3299" frameHeight="2505" />
<SubTexture name="na_scythe oo0002" x="1406" y="1319" width="701" height="1313" frameX="-1358" frameY="-107" frameWidth="3299" frameHeight="2505" />
<SubTexture name="na_scythe ee0000" x="2107" y="1319" width="701" height="1313" frameX="-1358" frameY="-107" frameWidth="3299" frameHeight="2505" />
<SubTexture name="na_scythe ee0001" x="2107" y="1319" width="701" height="1313" frameX="-1358" frameY="-107" frameWidth="3299" frameHeight="2505" />
<SubTexture name="na_scythe ee0002" x="2984" y="0" width="701" height="1313" frameX="-1358" frameY="-107" frameWidth="3299" frameHeight="2505" />
<SubTexture name="na_scythe aa0000" x="3685" y="0" width="702" height="1313" frameX="-1358" frameY="-107" frameWidth="3299" frameHeight="2505" />
<SubTexture name="na_scythe aa0001" x="3685" y="0" width="702" height="1313" frameX="-1358" frameY="-107" frameWidth="3299" frameHeight="2505" />
<SubTexture name="na_scythe aa0002" x="3685" y="1313" width="702" height="1313" frameX="-1358" frameY="-107" frameWidth="3299" frameHeight="2505" />
<SubTexture name="na_scythe turn0000" x="3685" y="1313" width="702" height="1313" frameX="-1358" frameY="-107" frameWidth="3299" frameHeight="2505" />
<SubTexture name="na_scythe turn0001" x="0" y="0" width="737" height="1319" frameX="-1356" frameY="-103" frameWidth="3299" frameHeight="2505" />
<SubTexture name="na_scythe turn0002" x="0" y="0" width="737" height="1319" frameX="-1356" frameY="-103" frameWidth="3299" frameHeight="2505" />
<SubTexture name="na_scythe turn0003" x="737" y="0" width="745" height="1319" frameX="-1356" frameY="-103" frameWidth="3299" frameHeight="2505" />
<SubTexture name="na_scythe turn0004" x="737" y="0" width="745" height="1319" frameX="-1356" frameY="-103" frameWidth="3299" frameHeight="2505" />
<SubTexture name="na_scythe turn0005" x="1482" y="0" width="751" height="1319" frameX="-1356" frameY="-103" frameWidth="3299" frameHeight="2505" />
<SubTexture name="na_scythe turn0006" x="1482" y="0" width="751" height="1319" frameX="-1356" frameY="-103" frameWidth="3299" frameHeight="2505" />
<SubTexture name="na_scythe turn0007" x="2233" y="0" width="751" height="1319" frameX="-1356" frameY="-103" frameWidth="3299" frameHeight="2505" />
</TextureAtlas>
